{
  "chapter": "परिसंचरण तंत्र (Circulatory System)",
  "subject": "Biology",
  "isPremium": false,
  "questions": [
    {
      "id": "q_514",
      "type": "standard",
      "question": "'दोहरा परसचंरण' को _______ म नह देखा जा सकता ह।ै",
      "options": [
        "मढक",
        "गरुड़",
        "मछली",
        "साँप"
      ],
      "correctIndex": 2,
      "explanation": "सही उत्तर विकल्प (C) अर्थात मछली है।\n\nयह प्रश्न RRB Group D 22 /8/2022 Shift 2 2022 में पूछा गया था।",
      "examName": "RRB Group D 22 /8/2022 Shift 2",
      "examYear": "2022"
    },
    {
      "id": "q_515",
      "type": "standard",
      "question": "नम्नलखत म स ेकौन-सा कथन, हृदय स ेफेफड़ा तक रुधर के परवहन का सही वणन करता ह?ै",
      "options": [
        "वऑक्सीजनत रुधर बाए नलय से फेफड़ा तक पंप कया जाता है।",
        "ऑक्सीजनत रुधर फेफड़ा से दाहन ेअलद तक जाता है।",
        "ऑक्सीजनत रुधर शोधन के लए बाए नलय से फेफड़ा तक प्रवाहत होता है।",
        "वऑक्सीजनत रुधर दाहन ेनलय से फेफड़ा तक पंप कया जाता है।"
      ],
      "correctIndex": 3,
      "explanation": "सही उत्तर विकल्प (D) अर्थात वऑक्सीजनत रुधर दाहन ेनलय से फेफड़ा तक पंप कया जाता है। है।\n\nयह प्रश्न RRB Technician Grade III 09/03/2026 9:00 AM - 10:30 AM 2026 में पूछा गया था।",
      "examName": "RRB Technician Grade III 09/03/2026 9:00 AM - 10:30 AM",
      "examYear": "2026"
    },
    {
      "id": "q_516",
      "type": "standard",
      "question": "नम्नलखत म स ेकस जानवर का हृदय दो कक्षीय होता ह?ै",
      "options": [
        "मछली",
        "सरीसृप",
        "स्तनधारी",
        "पक्षी"
      ],
      "correctIndex": 0,
      "explanation": "सही उत्तर विकल्प (A) अर्थात मछली है।\n\nयह प्रश्न RRB Group D 14 /9/2022 Shift 1 2022 में पूछा गया था।",
      "examName": "RRB Group D 14 /9/2022 Shift 1",
      "examYear": "2022"
    },
    {
      "id": "q_517",
      "type": "standard",
      "question": "नम्नलखत म स ेकस उपकरण का उपयोग रक्तदाब को मापने के लए कया जाता ह?ै",
      "options": [
        "स्पेक्टोफोटोमीटर",
        "स्फग्मोमैनोमीटर",
        "यूरनोमीटर",
        "हीमोग्लोबन मीटर"
      ],
      "correctIndex": 1,
      "explanation": "सही उत्तर विकल्प (B) अर्थात स्फग्मोमैनोमीटर है।\n\nयह प्रश्न RRB Group D 1 /9/2022 Shift 2 2022 में पूछा गया था।",
      "examName": "RRB Group D 1 /9/2022 Shift 2",
      "examYear": "2022"
    },
    {
      "id": "q_518",
      "type": "standard",
      "question": "मानव परसचंरण तंत्र म, सभी शराए रक्त को द्वदय क ओर ले जाती ह। फुफ्फुसीय शरा और अन्य शराआ म क्या अंतर ह?ै",
      "options": [
        "फुफ्फुसीय शरा ऑक्सीजन यक्ुत रक्त ल ेजाती है।",
        "फुफ्फुसीय शरा म रक्त का प्रवाह दाब के साथ होता है।",
        "फुफ्फुसीय शरा म एक छोटी अवकाशका (lumen) होती है।",
        "फुफ्फुसीय शरा म कोइ वाल्व नह होता है।"
      ],
      "correctIndex": 0,
      "explanation": "सही उत्तर विकल्प (A) अर्थात फुफ्फुसीय शरा ऑक्सीजन यक्ुत रक्त ल ेजाती है। है।\n\nयह प्रश्न RRB Group D 5 /9/2022 Shift 2 2022 में पूछा गया था।",
      "examName": "RRB Group D 5 /9/2022 Shift 2",
      "examYear": "2022"
    },
    {
      "id": "q_519",
      "type": "standard",
      "question": "रव खलेते समय अपने घुटने म चोटल हो गया और उसम स ेखनू बह रहा था। कुछ समय बाद, उसने देखा क खनू बहना बदं हो गया ह ैऔर एक गहरे लाल रंग का थक्का घाव को भर गया ह।ै कस प्रकार क कोशकाएँ रक्त के थक्के जमने म मदद करती ह?",
      "options": [
        "इोसनोफल्स",
        "प्लटेलटेस्",
        "लाल रक्त कणकाएँ",
        "लम्फोसाइटस्"
      ],
      "correctIndex": 1,
      "explanation": "सही उत्तर विकल्प (B) अर्थात प्लटेलटेस् है।\n\nयह प्रश्न RRB Group D 28 /9/2022 Shift 2 2022 में पूछा गया था।",
      "examName": "RRB Group D 28 /9/2022 Shift 2",
      "examYear": "2022"
    },
    {
      "id": "q_520",
      "type": "standard",
      "question": "हृदय मेम्ब्रने (झल्ली) क दो परता स ेढका होता ह।ै इन झल्लया को क्या कहा जाता ह?ै",
      "options": [
        "पल्मोनरी मेम्ब्रने",
        "पेरकाडयल मेम्ब्रने",
        "प्रीकेवल मेम्ब्रने",
        "सस्टेमेटक मेम्ब्रने"
      ],
      "correctIndex": 1,
      "explanation": "सही उत्तर विकल्प (B) अर्थात पेरकाडयल मेम्ब्रने है।\n\nयह प्रश्न RRB Group D 1 Nov 2018 Shift 2 2018 में पूछा गया था।",
      "examName": "RRB Group D 1 Nov 2018 Shift 2",
      "examYear": "2018"
    },
    {
      "id": "q_521",
      "type": "standard",
      "question": "दाए अटयम और दाए वटकल के बीच दाए औरक्यलुो वटक्यलुर- सप्ेटम पर मौजूद वाल्व को क्या कहा जाता ह?ै",
      "options": [
        "बाइकस्पड वॉल्व",
        "पल्मोनरी वाल्व",
        "सस्टेमेटक वाल्व",
        "टाइकस्पड InstBack to Telegram"
      ],
      "correctIndex": 3,
      "explanation": "सही उत्तर विकल्प (D) अर्थात टाइकस्पड InstBack to Telegram है।\n\nयह प्रश्न RRB Group D 1 Nov 2018 Shift 1 2018 में पूछा गया था।",
      "examName": "RRB Group D 1 Nov 2018 Shift 1",
      "examYear": "2018"
    },
    {
      "id": "q_522",
      "type": "standard",
      "question": "कस प्रकार क रक्त वाहका क भत्तया ंमोटी और लचीली होती ह ताक वह उच्च दाब को सहन कर सके?",
      "options": [
        "केशका",
        "शरा",
        "शरका",
        "धमनी"
      ],
      "correctIndex": 3,
      "explanation": "सही उत्तर विकल्प (D) अर्थात धमनी है।\n\nयह प्रश्न RRB Level 01 Stage I 10/02/2026 9:00 AM - 10:30 AM 2026 में पूछा गया था।",
      "examName": "RRB Level 01 Stage I 10/02/2026 9:00 AM - 10:30 AM",
      "examYear": "2026"
    },
    {
      "id": "q_523",
      "type": "standard",
      "question": "मानव शरीर म इसंुलन का क्या काय ह?ै",
      "options": [
        "यह फेफड़ा को ऑक्सीजन क आपूत करता है।",
        "यह रक्त के प्रवाह को नयंत्रत करता है।",
        "यह शरीर द्वारा ग्लकूोज और वसा के उपयोग और भडंारण को नयंत्रत करता है।",
        "यह हृदय को फ़ल्टर कए गए रक्त क आपूत करता है।"
      ],
      "correctIndex": 2,
      "explanation": "सही उत्तर विकल्प (C) अर्थात यह शरीर द्वारा ग्लकूोज और वसा के उपयोग और भडंारण को नयंत्रत करता है। है।\n\nयह प्रश्न RRB NTPC CBT-I : 22 Feb 2021 Shift 2 2021 में पूछा गया था।",
      "examName": "RRB NTPC CBT-I : 22 Feb 2021 Shift 2",
      "examYear": "2021"
    },
    {
      "id": "q_524",
      "type": "standard",
      "question": "यद द्ववलनी (मटल) कपाट ठक स ेबदं होने म वफल रहता ह,ै तो नलय के सकंुचन के दौरान कस तत्काल प्रभाव क सबस ेअधक सभंावना ह?ै",
      "options": [
        "बाएँ नलय से बाएँ अलद म रक्त का वपरीत प्रवाह",
        "दाएँ नलय स ेदाएँ अलद म रक्त का वपरीत प्रवाह",
        "नलय म ऑक्सीजनटेेड और डीऑक्सीजनटेेड रक्त का मश्रण",
        "फेफड़ा म रक्त का प्रवाह कम होना"
      ],
      "correctIndex": 0,
      "explanation": "सही उत्तर विकल्प (A) अर्थात बाएँ नलय से बाएँ अलद म रक्त का वपरीत प्रवाह है।\n\nयह प्रश्न RRB JE 20/02/2026 4:30 PM - 6:00 PM 2026 में पूछा गया था।",
      "examName": "RRB JE 20/02/2026 4:30 PM - 6:00 PM",
      "examYear": "2026"
    },
    {
      "id": "q_525",
      "type": "standard",
      "question": "नम्नलखत म स ेकौन-सा कथन सही तरीके स ेवणन करता ह ैक शराआ म वाल्व होते ह जबक धमनया म नह होते ह?",
      "options": [
        "शराए नम्न दाब पर रक्त ल ेजाती ह और रक्त के उल्टे प्रवाह को रोकने के लए वाल्व क आवश्यकता होती है।",
        "शराए उच्च दाब म रक्त ल ेजाती ह, इसलए वाल्व इस ेफटन ेस ेरोकत ेह।",
        "धमनया ंऑक्सीजन यक्ुत रक्त ल ेजाती ह और उन्ह वाल्व क आवश्यकता नह होती है।",
        "धमनया ंशरीर के अंदरूनी हस्स ेम स्थत होती ह और पेशी द्वारा समथत होती ह।"
      ],
      "correctIndex": 0,
      "explanation": "सही उत्तर विकल्प (A) अर्थात शराए नम्न दाब पर रक्त ल ेजाती ह और रक्त के उल्टे प्रवाह को रोकने के लए वाल्व क आवश्यकता होती है। है।\n\nयह प्रश्न RRB Technician Grade III 10/03/2026 4:30 PM - 6:00 PM 2026 में पूछा गया था।",
      "examName": "RRB Technician Grade III 10/03/2026 4:30 PM - 6:00 PM",
      "examYear": "2026"
    },
    {
      "id": "q_526",
      "type": "standard",
      "question": "AIDS का वषाणु शरीर म _____ को नष्ट कर देता ह।ै",
      "options": [
        "लाल रक्त कणकाआ",
        "परसंचरण तंत्र",
        "यकृत",
        "प्रतरक्षा तंत्र"
      ],
      "correctIndex": 3,
      "explanation": "सही उत्तर विकल्प (D) अर्थात प्रतरक्षा तंत्र है।\n\nयह प्रश्न RRB JE CBT I - : 1 June 2019 Shift 1 2019 में पूछा गया था।",
      "examName": "RRB JE CBT I - : 1 June 2019 Shift 1",
      "examYear": "2019"
    },
    {
      "id": "q_527",
      "type": "standard",
      "question": "मानव म नाइटोजन यक्ुत अपशष्ट पदाथ उत्पन्न करने वाली उपापचय क्रयाआ को कसके द्वारा हटाया जाता ह?ै",
      "options": [
        "संवहनी तंत्र",
        "उत्सजन तंत्र",
        "परसंचरण तंत्र",
        "श्वसन तंत्र"
      ],
      "correctIndex": 1,
      "explanation": "सही उत्तर विकल्प (B) अर्थात उत्सजन तंत्र है।\n\nयह प्रश्न RRB ALP CBT-I 2024 : 28 Nov, 2024 Shift 2 2024 में पूछा गया था।",
      "examName": "RRB ALP CBT-I 2024 : 28 Nov, 2024 Shift 2",
      "examYear": "2024"
    },
    {
      "id": "q_528",
      "type": "standard",
      "question": "नम्नलखत म स ेकस कारण, हृदय के नलय म मोटी पेशीय भत्तया ँमौजूद होती ह?",
      "options": [
        "रक्त को आलद म प्रवेश करन ेस ेपहल ेभडंारत करन ेके लए",
        "उच्च दाब के साथ रक्त को पंप करन ेके लए",
        "शरीर और फेफड़ा स ेरक्त प्राप्त करन ेके लए",
        "हृदय स्पंद और लय को नयंत्रत करन ेके लए"
      ],
      "correctIndex": 1,
      "explanation": "सही उत्तर विकल्प (B) अर्थात उच्च दाब के साथ रक्त को पंप करन ेके लए है।\n\nयह प्रश्न RRB ALP CBT 1 18/02/2026 12:30 PM - 1:30 PM 2026 में पूछा गया था।",
      "examName": "RRB ALP CBT 1 18/02/2026 12:30 PM - 1:30 PM",
      "examYear": "2026"
    },
    {
      "id": "q_529",
      "type": "standard",
      "question": "नम्नलखत म स ेक्या परसचंरण तंत्र का भाग नह ह?ै",
      "options": [
        "बड़ी आतं",
        "रक्त",
        "हृदय",
        "धमनया Index Youtube"
      ],
      "correctIndex": 0,
      "explanation": "सही उत्तर विकल्प (A) अर्थात बड़ी आतं है।\n\nयह प्रश्न RRB NTPC CBT-I : 28 Dec 2020 Shift 2 2020 में पूछा गया था।",
      "examName": "RRB NTPC CBT-I : 28 Dec 2020 Shift 2",
      "examYear": "2020"
    },
    {
      "id": "q_530",
      "type": "standard",
      "question": "रक्तदाब के सबंधं म नम्नलखत म स ेकौन-सा कथन असत्य ह?ै",
      "options": [
        "धमनया क तुलना म शराआ म दाब बहुत अधक होता है।",
        "नलय संकुचन के दौरान होन ेवाल ेदाब को प्रकुंचन दाब कहा जाता है और नलय शथलन के दौरान होन ेवाल ेदाब को अनुशथलन दाब कहा जाता है।",
        "सामान्य प्रकुंचक दाब लगभग 120 mm Hg होता ह ैऔर अनुशथलक दाब 80 mm Hg होता है।",
        "दाब को स्फाइग्मोमैनोमीटर का उपयोग करके मापा जाता है।"
      ],
      "correctIndex": 0,
      "explanation": "सही उत्तर विकल्प (A) अर्थात धमनया क तुलना म शराआ म दाब बहुत अधक होता है। है।\n\nयह प्रश्न RRB Group D 28 /9/2022 Shift 3 2022 में पूछा गया था।",
      "examName": "RRB Group D 28 /9/2022 Shift 3",
      "examYear": "2022"
    },
    {
      "id": "q_531",
      "type": "standard",
      "question": "रक्तदाब को दो माना के रूप म दज कया जाता ह:ै _________ दाब, जो हृदय के सकंुचन के समय मापा जाता ह,ै तथा ___________ दाब, जो हृदय के शथल होने के समय मापा जाता ह।ै",
      "options": [
        "प्रकुंचन; अनुशथलन ( Systolic; Diastolic)",
        "अनुशथलन; शरा ( Diastolic; Venous)",
        "अधकतम; प्रकुंचन ( Maximum; Systolic)",
        "अनुशथलन; प्रकुंचन ( Diastolic; Systolic)"
      ],
      "correctIndex": 0,
      "explanation": "सही उत्तर विकल्प (A) अर्थात प्रकुंचन; अनुशथलन ( Systolic; Diastolic) है।\n\nयह प्रश्न RRB Technician Grade III 09/03/2026 12:45 PM - 2:15 PM 2026 में पूछा गया था।",
      "examName": "RRB Technician Grade III 09/03/2026 12:45 PM - 2:15 PM",
      "examYear": "2026"
    },
    {
      "id": "q_532",
      "type": "standard",
      "question": "नम्नलखत सरंचनाआ म स ेकस सरंचना के माध्यम स ेमूत्र, वक्ृक स ेमूत्राशय वस्त म जाता ह?ै",
      "options": [
        "धमनी",
        "शरा",
        "महाशरा",
        "गवीनी"
      ],
      "correctIndex": 3,
      "explanation": "सही उत्तर विकल्प (D) अर्थात गवीनी है।\n\nयह प्रश्न RRB Level 01 Stage I 03/02/2026 4:30 PM - 6:00 PM 2026 में पूछा गया था।",
      "examName": "RRB Level 01 Stage I 03/02/2026 4:30 PM - 6:00 PM",
      "examYear": "2026"
    },
    {
      "id": "q_533",
      "type": "standard",
      "question": "स्तनधारी जंतुआ का _________ होता ह।ै",
      "options": [
        "एक कक्षीय हृदय",
        "चार कक्षीय हृदय",
        "दो कक्षीय हृदय",
        "तीन कक्षीय हृदय"
      ],
      "correctIndex": 1,
      "explanation": "सही उत्तर विकल्प (B) अर्थात चार कक्षीय हृदय है।\n\nयह प्रश्न RRB Group D 9/10/2018 Shift 1 2018 में पूछा गया था।",
      "examName": "RRB Group D 9/10/2018 Shift 1",
      "examYear": "2018"
    },
    {
      "id": "q_534",
      "type": "standard",
      "question": "मनुष्या म परसचंरण तंत्र क कुछ वशषेताए नीच ेदी गइ ह। गलत वकल्प चनु।",
      "options": [
        "उच्च रक्तचाप नसा के संकुचन के कारण होता है",
        "प्लटेलटेस रक्त का थक्का जमान ेम मदद करत ेह्",
        "लसीका को ऊतक द्रव भी कहा जाता है",
        "केशकाए मलकर शराए बनाती ह"
      ],
      "correctIndex": 0,
      "explanation": "सही उत्तर विकल्प (A) अर्थात उच्च रक्तचाप नसा के संकुचन के कारण होता है है।\n\nयह प्रश्न RRB Group D 22 /8/2022 Shift 3 2022 में पूछा गया था।",
      "examName": "RRB Group D 22 /8/2022 Shift 3",
      "examYear": "2022"
    },
    {
      "id": "q_535",
      "type": "standard",
      "question": "मानव हृदय म अनुशथलन के दौरान नम्नलखत म स ेकौन-सी घटना घटत होती ह?ै",
      "options": [
        "रक्त फेफड़ा म प्रवेश करता है।",
        "रक्त नलय म प्रवेश करता है।",
        "रक्त नलय से बाहर नकलता है।",
        "रक्त महाधमनी म प्रवेश करता है।"
      ],
      "correctIndex": 1,
      "explanation": "सही उत्तर विकल्प (B) अर्थात रक्त नलय म प्रवेश करता है। है।\n\nयह प्रश्न RRB Group D 18 /9/2022 Shift 2 2022 में पूछा गया था।",
      "examName": "RRB Group D 18 /9/2022 Shift 2",
      "examYear": "2022"
    },
    {
      "id": "q_536",
      "type": "standard",
      "question": "कसी अंग या ऊतक तक पहुचँने पर, धमनयाँ छोटी-छोटी वाहकाआ म वभाजत हो जाती ह। सबस ेछोटी वाहकाआ क भत्तया ँएक कोशका जतनी मोटी होती ह जन्ह __________ कहा जाता ह।ै",
      "options": [
        "केशकाएँ",
        "शराएँ",
        "धमनयाँ",
        "धमनकाएँ"
      ],
      "correctIndex": 0,
      "explanation": "सही उत्तर विकल्प (A) अर्थात केशकाएँ है।\n\nयह प्रश्न RRB ALP CBT 1 17/02/2026 9:00 AM - 10:00 AM 2026 में पूछा गया था।",
      "examName": "RRB ALP CBT 1 17/02/2026 9:00 AM - 10:00 AM",
      "examYear": "2026"
    },
    {
      "id": "q_537",
      "type": "standard",
      "question": "नम्नलखत म स ेकस प्रावस्था के दौरान रक्त द्वारा धमनी क भत्त पर प्रकंुचन रक्तदाब लगाया जाता ह?ै",
      "options": [
        "अलद संकुचन",
        "नलय शथलन",
        "अलद शथलन",
        "नलय संकुचन InstBack to Telegram"
      ],
      "correctIndex": 3,
      "explanation": "सही उत्तर विकल्प (D) अर्थात नलय संकुचन InstBack to Telegram है।\n\nयह प्रश्न RRB Group D 24 /8/2022 Shift 1 2022 में पूछा गया था।",
      "examName": "RRB Group D 24 /8/2022 Shift 1",
      "examYear": "2022"
    },
    {
      "id": "q_538",
      "type": "standard",
      "question": "नम्नलखत म स ेकस जीव का हृदय तीन कक्षीय होता ह?ै",
      "options": [
        "चड़या",
        "मढक",
        "मछली",
        "मानव"
      ],
      "correctIndex": 1,
      "explanation": "सही उत्तर विकल्प (B) अर्थात मढक है।\n\nयह प्रश्न RRB Group D 2 /9/2022 Shift 2 2022 में पूछा गया था।",
      "examName": "RRB Group D 2 /9/2022 Shift 2",
      "examYear": "2022"
    },
    {
      "id": "q_539",
      "type": "standard",
      "question": "उस वकल्प का चयन कजय ेजो परसचंरण तंत्र के बारे म सत्य नही ह।ै",
      "options": [
        "धमनया म रक्त उच्च दाब पर प्रवाहत होता है।",
        "मानव ह्रदय खुल ेहुए हाथ के आकार का होता है",
        "रक्त के तरल घटक को प्लाज्मा कहा जाता है।",
        "रक्त शरीर के वजन का लगभग 7-8% बनाता है"
      ],
      "correctIndex": 1,
      "explanation": "सही उत्तर विकल्प (B) अर्थात मानव ह्रदय खुल ेहुए हाथ के आकार का होता है है।\n\nयह प्रश्न RRB Group D 4/10/2018 Shift 2 2018 में पूछा गया था।",
      "examName": "RRB Group D 4/10/2018 Shift 2",
      "examYear": "2018"
    },
    {
      "id": "q_540",
      "type": "standard",
      "question": "नम्नलखत म स ेकौन सा पूरे शरीर म प्रवाहत होता ह,ै और चोट के स्थान पर रक्त का थक्का बनाने म मदद करके रक्तस्राव को रोकता ह?ै",
      "options": [
        "श्वेत रक्त कणकाए (WBC)",
        "प्लटेलटेस्",
        "प्लाज्मा",
        "लाल रक्त कणकाए (RBC)"
      ],
      "correctIndex": 1,
      "explanation": "सही उत्तर विकल्प (B) अर्थात प्लटेलटेस् है।\n\nयह प्रश्न RRB Group D 13 /9/2022 Shift 3 2022 में पूछा गया था।",
      "examName": "RRB Group D 13 /9/2022 Shift 3",
      "examYear": "2022"
    },
    {
      "id": "q_541",
      "type": "standard",
      "question": "नम्नलखत म स ेकौन-सी नलका ह ैजो हृदय स ेनकलती ह ैऔर शरीर म वभन्न अंगा म रक्त सचंारत करती ह?ै",
      "options": [
        "शराएँ",
        "फेफड़े तक जान ेवाली रक्त कोशका",
        "धमनी",
        "फुफुसीय धमनयाँ"
      ],
      "correctIndex": 2,
      "explanation": "सही उत्तर विकल्प (C) अर्थात धमनी है।\n\nयह प्रश्न RRB Group D 5 Nov 2018 Shift 1 2018 में पूछा गया था।",
      "examName": "RRB Group D 5 Nov 2018 Shift 1",
      "examYear": "2018"
    },
    {
      "id": "q_542",
      "type": "standard",
      "question": "रक्त का तरल मैटक्स क्या कहलाता ह?ै",
      "options": [
        "RBC (लाल रक्त कणकाएँ)",
        "प्लाज्मा",
        "प्लटेलटेस्",
        "WBC (श्वेत रक्त कणकाएँ)"
      ],
      "correctIndex": 1,
      "explanation": "सही उत्तर विकल्प (B) अर्थात प्लाज्मा है।\n\nयह प्रश्न RRB Group D 20 /9/2022 Shift 3 2022 में पूछा गया था।",
      "examName": "RRB Group D 20 /9/2022 Shift 3",
      "examYear": "2022"
    },
    {
      "id": "q_543",
      "type": "standard",
      "question": "वह वकल्प चनु जो सवंहनी प्रणाली के बारे म सत्य नह है",
      "options": [
        "रक्त केवल सफेद संवहनी संयोजी ऊतक है",
        "संवहनी प्रणाली शरीर के वजन का लगभग 7-8% बनाती है",
        "कसी वयस्क व्यक्त म लगभग 6.8 लीटर रक्त होता है",
        "मानव लाल रक्त कोशकाआ का जीवन काल 115-120 दन है।"
      ],
      "correctIndex": 0,
      "explanation": "सही उत्तर विकल्प (A) अर्थात रक्त केवल सफेद संवहनी संयोजी ऊतक है है।\n\nयह प्रश्न RRB Group D 3/10/2018 Shift 2 2018 में पूछा गया था।",
      "examName": "RRB Group D 3/10/2018 Shift 2",
      "examYear": "2018"
    },
    {
      "id": "q_544",
      "type": "standard",
      "question": "स्वपोषी जीव बाहरी पदाथा को कैस ेग्रहण करते ह और सयू के प्रकाश क उपस्थत म उन्ह संचत ऊजा के रूप म कैस ेपरवतत करते ह?",
      "options": [
        "परसंचरण",
        "गत",
        "पाचन",
        "प्रकाश संषेण Index Youtube"
      ],
      "correctIndex": 3,
      "explanation": "सही उत्तर विकल्प (D) अर्थात प्रकाश संषेण Index Youtube है।\n\nयह प्रश्न RRB Technician Grade III : 29 Dec, 2024 Shift 1 2024 में पूछा गया था।",
      "examName": "RRB Technician Grade III : 29 Dec, 2024 Shift 1",
      "examYear": "2024"
    },
    {
      "id": "q_545",
      "type": "standard",
      "question": "नम्न आकृत मानव हृदय को दशाती ह।ै LA = बाया ँअलद; LV = बाया ँनलय; RA = दाया ँअलद; RV = दाया ँनलय। वाल्व कहाँ स्थत ह?",
      "options": [
        "1, 2, 3, 4, 5 और 6 सभी पदा पर",
        "1, 2, 4 और 6 पदा पर",
        "2, 3, 4 और 5 पदा पर",
        "4, 5 और 6 पदा पर"
      ],
      "correctIndex": 2,
      "explanation": "सही उत्तर विकल्प (C) अर्थात 2, 3, 4 और 5 पदा पर है।\n\nयह प्रश्न RRB Group D 6/10/2022 Shift 1 2022 में पूछा गया था।",
      "examName": "RRB Group D 6/10/2022 Shift 1",
      "examYear": "2022"
    },
    {
      "id": "q_546",
      "type": "standard",
      "question": "फेफड़ा स ेऑक्सीजन यक्ुत रक्त हृदय म कहाँ आता ह?ै",
      "options": [
        "फुफ्फुसीय धमनयाँ",
        "बाया ँनलय",
        "फुफ्फुसीय शराएँ",
        "बाया ँआलद"
      ],
      "correctIndex": 3,
      "explanation": "सही उत्तर विकल्प (D) अर्थात बाया ँआलद है।\n\nयह प्रश्न RRB Technician Grade III : 27 Dec, 2024 Shift 2 2024 में पूछा गया था।",
      "examName": "RRB Technician Grade III : 27 Dec, 2024 Shift 2",
      "examYear": "2024"
    },
    {
      "id": "q_547",
      "type": "standard",
      "question": "मनुष्य जैस ेकुछ प्राणया के हृदय म ऑक्सीजन रहत रक्त को ऑक्सीजन यक्ुत रक्त स ेअलग क्या रखा जाता ह?ै",
      "options": [
        "मांसपेशया क वृद्ध और कायप्रणाली म सहायता करन ेके लए",
        "फेफड़ा म रक्त का ऑक्सीकरण अधकतम करन ेके लए",
        "शरीर का तापमान स्थर रखन ेम सहायता करन ेके लए",
        "बड़े शरीर वाल ेजानवर को ऑक्सीजन प्रदान करन ेके लए"
      ],
      "correctIndex": 2,
      "explanation": "सही उत्तर विकल्प (C) अर्थात शरीर का तापमान स्थर रखन ेम सहायता करन ेके लए है।\n\nयह प्रश्न RRB Group D 14 /9/2022 Shift 1 2022 में पूछा गया था।",
      "examName": "RRB Group D 14 /9/2022 Shift 1",
      "examYear": "2022"
    },
    {
      "id": "q_548",
      "type": "standard",
      "question": "वक्ृक वफलता का उपचार समय-समय पर कडनी मशीन स ेकया जाता ह।ै इस प्रक्रया को ______ के रूप म जाना जाता ह।ै",
      "options": [
        "मलोत्सजन",
        "उपापचय",
        "हेमोडायलसस",
        "परसंचरण"
      ],
      "correctIndex": 2,
      "explanation": "सही उत्तर विकल्प (C) अर्थात हेमोडायलसस है।\n\nयह प्रश्न RRB NTPC CBT-I : 16 Jan 2021 Shift 2 2021 में पूछा गया था।",
      "examName": "RRB NTPC CBT-I : 16 Jan 2021 Shift 2",
      "examYear": "2021"
    },
    {
      "id": "q_549",
      "type": "standard",
      "question": "नम्न म स ेकन प्राणया म पूरे शरीर म रक्त प्रवाह के प्रत्यके चक्र के दौरान, रक्त केवल एक बार हृदय स ेहोकर गजुरता ह?ै",
      "options": [
        "स्तनधारी",
        "सरीसृप",
        "पक्षी",
        "मत्स्य"
      ],
      "correctIndex": 3,
      "explanation": "सही उत्तर विकल्प (D) अर्थात मत्स्य है।\n\nयह प्रश्न RRB Group D 22 /9/2022 Shift 2 2022 में पूछा गया था।",
      "examName": "RRB Group D 22 /9/2022 Shift 2",
      "examYear": "2022"
    },
    {
      "id": "q_550",
      "type": "standard",
      "question": "मछलया का हृदय _____ कक्षीय होता ह।ै",
      "options": [
        "एकल",
        "तीन",
        "चार",
        "दो"
      ],
      "correctIndex": 3,
      "explanation": "सही उत्तर विकल्प (D) अर्थात दो है।\n\nयह प्रश्न RRB Group D 17 Sept 2018 Shift 2 2018 में पूछा गया था।",
      "examName": "RRB Group D 17 Sept 2018 Shift 2",
      "examYear": "2018"
    },
    {
      "id": "q_551",
      "type": "standard",
      "question": "नम्नलखत म स ेकौन-सा कथन गलत ह?ै",
      "options": [
        "रक्त शरीर को रोगा से बचाता है।",
        "रक्त फेफड़ा से ऑक्सीजन को शरीर के अन्य भागा म ल ेजाता है।",
        "रक्त संवेदी अंगो म सहायता करता है।",
        "रक्त काबन डाइऑक्साइड को शरीर क कोशकाआ से फेफड़ा तक ले जाता है। InstBack to Telegram"
      ],
      "correctIndex": 2,
      "explanation": "सही उत्तर विकल्प (C) अर्थात रक्त संवेदी अंगो म सहायता करता है। है।\n\nयह प्रश्न RRB NTPC CBT-I : 18 Jan 2021 Shift 2 2021 में पूछा गया था।",
      "examName": "RRB NTPC CBT-I : 18 Jan 2021 Shift 2",
      "examYear": "2021"
    },
    {
      "id": "q_552",
      "type": "standard",
      "question": "मानव हृदय म फुफ्फुस शरा _________ स ेजुड़ी होती ह।ै",
      "options": [
        "दाया ँअलन्द",
        "बाया ँनलय",
        "बाया ँअलन्द",
        "दाया ँनलय"
      ],
      "correctIndex": 2,
      "explanation": "सही उत्तर विकल्प (C) अर्थात बाया ँअलन्द है।\n\nयह प्रश्न RRB Group D 6/10/2022 Shift 2 2022 में पूछा गया था।",
      "examName": "RRB Group D 6/10/2022 Shift 2",
      "examYear": "2022"
    },
    {
      "id": "q_553",
      "type": "standard",
      "question": "मनुष्या म सामान्य प्रकंुचन और अनुशथलन दबाव क्रमशः __________ होता ह।ै",
      "options": [
        "150 और 75 mm Hg",
        "140 और 90 mm Hg",
        "120 और 80 mm Hg",
        "100 और 60 mm Hg"
      ],
      "correctIndex": 2,
      "explanation": "सही उत्तर विकल्प (C) अर्थात 120 और 80 mm Hg है।\n\nयह प्रश्न RRB Group D 23 /8/2022 Shift 2 2022 में पूछा गया था।",
      "examName": "RRB Group D 23 /8/2022 Shift 2",
      "examYear": "2022"
    },
    {
      "id": "q_554",
      "type": "standard",
      "question": "नम्नलखत म स ेकस जानवर म प्रत्यके चक्र के दौरान रक्त दो बार हृदय से गजुरता ह?ै",
      "options": [
        "स्तनधारी, मछली और सरीसृप",
        "मछली, पक्षी और सरीसृप",
        "स्तनधारी, पक्षी और सरीसृप",
        "स्तनधारी, पक्षी और मछली"
      ],
      "correctIndex": 2,
      "explanation": "सही उत्तर विकल्प (C) अर्थात स्तनधारी, पक्षी और सरीसृप है।\n\nयह प्रश्न RRB Group D 29 /9/2022 Shift 3 2022 में पूछा गया था।",
      "examName": "RRB Group D 29 /9/2022 Shift 3",
      "examYear": "2022"
    },
    {
      "id": "q_555",
      "type": "standard",
      "question": "उपकला ऊतका क कोशकाआ के बीच बहुत कम स्थान क्या होता ह?ै",
      "options": [
        "पेशया के संचलन को सुगम बनान ेके लए",
        "उन्ह वद्युत संकेता को प्रेषत करन ेम सक्षम बनान ेके लए",
        "पदाथा क पारगम्यता को नयंत्रत करन ेवाला एक प्रभावी अवरोध बनाने के लए",
        "तेजी स ेरक्त प्रवाह क होन ेदेन ेके लए"
      ],
      "correctIndex": 2,
      "explanation": "सही उत्तर विकल्प (C) अर्थात पदाथा क पारगम्यता को नयंत्रत करन ेवाला एक प्रभावी अवरोध बनाने के लए है।\n\nयह प्रश्न RRB Level 01 Stage I 26/12/2025 12:45 PM - 2:15 PM 2025 में पूछा गया था।",
      "examName": "RRB Level 01 Stage I 26/12/2025 12:45 PM - 2:15 PM",
      "examYear": "2025"
    },
    {
      "id": "q_556",
      "type": "standard",
      "question": "नम्नलखत म स ेकौन हृदय स ेगदु तक रक्त पहुचँाता ह?ै",
      "options": [
        "महाशरा",
        "वक्ृक शरा",
        "वक्ृक धमनी",
        "हृदय धमनी"
      ],
      "correctIndex": 2,
      "explanation": "सही उत्तर विकल्प (C) अर्थात वक्ृक धमनी है।\n\nयह प्रश्न RRB NTPC CBT-I : 22 Feb 2021 Shift 2 2021 में पूछा गया था।",
      "examName": "RRB NTPC CBT-I : 22 Feb 2021 Shift 2",
      "examYear": "2021"
    },
    {
      "id": "q_557",
      "type": "standard",
      "question": "मानव शरीर म कंकाल पेशया का मुख्य काय नम्नलखत म स ेक्या ह?ै",
      "options": [
        "हमारे शरीर म संचलन",
        "परसंचरण",
        "उत्सजन",
        "श्वसन"
      ],
      "correctIndex": 0,
      "explanation": "सही उत्तर विकल्प (A) अर्थात हमारे शरीर म संचलन है।\n\nयह प्रश्न RRB Level 01 Stage I 30/12/2025 9:00 AM - 10:30 AM 2025 में पूछा गया था।",
      "examName": "RRB Level 01 Stage I 30/12/2025 9:00 AM - 10:30 AM",
      "examYear": "2025"
    },
    {
      "id": "q_558",
      "type": "standard",
      "question": "मानव शरीर म श्वसन वणक कहा ँपाया जाता ह?ै",
      "options": [
        "श्वेत रक्त कोशकाआ म",
        "लाल रक्त कोशकाआ म",
        "प्लाज्मा और श्वेत रक्त कोशकाआ म",
        "रक्त प्लाज्मा म"
      ],
      "correctIndex": 1,
      "explanation": "सही उत्तर विकल्प (B) अर्थात लाल रक्त कोशकाआ म है।\n\nयह प्रश्न RRB Group D 24 /8/2022 Shift 2 2022 में पूछा गया था।",
      "examName": "RRB Group D 24 /8/2022 Shift 2",
      "examYear": "2022"
    },
    {
      "id": "q_559",
      "type": "standard",
      "question": "नम्नलखत म स ेकौन सा रक्त घटक थक्के के नमाण म सहायता करता ह?ै",
      "options": [
        "प्लटेलटेस",
        "प्लाज्मा प्रोटीन्",
        "श्वेत रुधराणु",
        "लाल रक्त कोशकाआ"
      ],
      "correctIndex": 0,
      "explanation": "सही उत्तर विकल्प (A) अर्थात प्लटेलटेस है।\n\nयह प्रश्न RRB Group D 23 /8/2022 Shift 3 2022 में पूछा गया था।",
      "examName": "RRB Group D 23 /8/2022 Shift 3",
      "examYear": "2022"
    },
    {
      "id": "q_560",
      "type": "standard",
      "question": "नम्नलखत म स ेकौन-सा सवंहनी प्रणाली के बारे म सत्य नह ह?ै",
      "options": [
        "मानव RBC का जीवन काल 115-120 दन है।",
        "नाड़ी प्रणाली शरीर के वजन का लगभग 7-8% बनाती है।",
        "रक्त सफेद या लाल संवहनी संयोजी ऊतक होता है।",
        "एक वयस्क व्यक्त म लगभग 5-6 लीटर रक्त होता है"
      ],
      "correctIndex": 2,
      "explanation": "सही उत्तर विकल्प (C) अर्थात रक्त सफेद या लाल संवहनी संयोजी ऊतक होता है। है।\n\nयह प्रश्न RRB Group D 3/10/2018 Shift 1 2018 में पूछा गया था।",
      "examName": "RRB Group D 3/10/2018 Shift 1",
      "examYear": "2018"
    },
    {
      "id": "q_561",
      "type": "standard",
      "question": "नम्नलखत म स ेकौन सी वाहका रक्त को हृदय स ेफेफड़ा को छोड़कर शरीर के वभन्न अंगा तक ले जाती ह?ै",
      "options": [
        "फुफ्फुसीय धमनी",
        "फुफ्फुसीय शरा",
        "महाशरा",
        "महाधमनी Index Youtube"
      ],
      "correctIndex": 3,
      "explanation": "सही उत्तर विकल्प (D) अर्थात महाधमनी Index Youtube है।\n\nयह प्रश्न RRB Group D 11/10/2022 Shift 3 2022 में पूछा गया था।",
      "examName": "RRB Group D 11/10/2022 Shift 3",
      "examYear": "2022"
    },
    {
      "id": "q_562",
      "type": "standard",
      "question": "वह वकल्प चनु जो सवंहन तंत्र के बारे म सत्य नह ह।ै",
      "options": [
        "रक्त कम दबाव म बहता है, झटके के साथ और उनम तेज होता है।",
        "यह शरीर के वजन का लगभग 7-8% बनाता है।",
        "रक्त को प्रायः पर जीवन क नदी कहा जाता है।",
        "मानव आरबीसी का जीवन काल 115-120 दन है।"
      ],
      "correctIndex": 0,
      "explanation": "सही उत्तर विकल्प (A) अर्थात रक्त कम दबाव म बहता है, झटके के साथ और उनम तेज होता है। है।\n\nयह प्रश्न RRB Group D 4/10/2018 Shift 1 2018 में पूछा गया था।",
      "examName": "RRB Group D 4/10/2018 Shift 1",
      "examYear": "2018"
    },
    {
      "id": "q_563",
      "type": "standard",
      "question": "हृदय का कौन-सा कोष्ठ वऑक्सीजनत रुधर को अक्सीजनन के लए फुफ्फुस म भजेता ह?ै",
      "options": [
        "बाया ंनलय",
        "दाया ंआलद",
        "दाया ंनलय",
        "बाया ंआलद"
      ],
      "correctIndex": 2,
      "explanation": "सही उत्तर विकल्प (C) अर्थात दाया ंनलय है।\n\nयह प्रश्न RRB ALP CBT 1 17/02/2026 4:00 PM - 5:00 PM 2026 में पूछा गया था।",
      "examName": "RRB ALP CBT 1 17/02/2026 4:00 PM - 5:00 PM",
      "examYear": "2026"
    },
    {
      "id": "q_564",
      "type": "standard",
      "question": "रक्तचाप वह बल ह:ै",
      "options": [
        "नसा के अंदर",
        "वटकुलर डायस्टोल के दौरान धमनी के अंदर",
        "वटकुलर सस्टोल के दौरान धमनी के अंदर",
        "रक्त वाहका क दीवार के वरुद्ध दबाव डालता है"
      ],
      "correctIndex": 3,
      "explanation": "सही उत्तर विकल्प (D) अर्थात रक्त वाहका क दीवार के वरुद्ध दबाव डालता है है।\n\nयह प्रश्न RRB NTPC CBT-I : 8 Mar 2021 Shift 1 2021 में पूछा गया था।",
      "examName": "RRB NTPC CBT-I : 8 Mar 2021 Shift 1",
      "examYear": "2021"
    },
    {
      "id": "q_565",
      "type": "standard",
      "question": "नम्नलखत म स ेकौन मूत्राशय के दाब को नयंत्रत करता ह?ै",
      "options": [
        "वक्ृक",
        "हृदय",
        "तंत्रका तंत्र",
        "रक्तचाप"
      ],
      "correctIndex": 2,
      "explanation": "सही उत्तर विकल्प (C) अर्थात तंत्रका तंत्र है।\n\nयह प्रश्न RRB ALP CBT-I 2024 : 27 Nov, 2024 Shift 3 2024 में पूछा गया था।",
      "examName": "RRB ALP CBT-I 2024 : 27 Nov, 2024 Shift 3",
      "examYear": "2024"
    },
    {
      "id": "q_566",
      "type": "standard",
      "question": "मानव हृदय म शीथलन के दौरान नम्नलखत म स ेकौन सी घटना घटत होती ह?ै",
      "options": [
        "रक्त नलय से बाहर नकलता है।",
        "रक्त महाधमनी म प्रवेश करता है।",
        "रक्त नलय म प्रवेश करता है।",
        "रक्त फेफड़ा म प्रवेश करता है।"
      ],
      "correctIndex": 2,
      "explanation": "सही उत्तर विकल्प (C) अर्थात रक्त नलय म प्रवेश करता है। है।\n\nयह प्रश्न RRB Group D 18/8/2022 Shift 2 2022 में पूछा गया था।",
      "examName": "RRB Group D 18/8/2022 Shift 2",
      "examYear": "2022"
    },
    {
      "id": "q_567",
      "type": "standard",
      "question": "प्रकंुचन दाब _________ का एक माप ह।ै",
      "options": [
        "नलयी संकुचन",
        "नलयी शथलन",
        "अलद संकुचन",
        "अलद शथलन"
      ],
      "correctIndex": 0,
      "explanation": "सही उत्तर विकल्प (A) अर्थात नलयी संकुचन है।\n\nयह प्रश्न RRB Group D 13 /9/2022 Shift 3 2022 में पूछा गया था।",
      "examName": "RRB Group D 13 /9/2022 Shift 3",
      "examYear": "2022"
    },
    {
      "id": "q_568",
      "type": "standard",
      "question": "कौन-सा अवलोकन इस कथन का सवात्तम समथन करता ह ैक मनुष्या म रक्त का दोहरा परसचंरण होता ह?ै",
      "options": [
        "एक पूण परसंचरण म रक्त हृदय म दो बार जाता है।",
        "एक पूण चक्र म हृदय म केवल एक बार रक्त जाता है।",
        "हृदय का दाहना भाग ऑक्सीजनत रक्त पंप करता है।",
        "हृदय म ऑक्सीजनत और वऑक्सीजनत रक्त का मश्रण।"
      ],
      "correctIndex": 0,
      "explanation": "सही उत्तर विकल्प (A) अर्थात एक पूण परसंचरण म रक्त हृदय म दो बार जाता है। है।\n\nयह प्रश्न RRB JE 19/02/2026 12:45 PM - 2:15 PM 2026 में पूछा गया था।",
      "examName": "RRB JE 19/02/2026 12:45 PM - 2:15 PM",
      "examYear": "2026"
    },
    {
      "id": "q_569",
      "type": "standard",
      "question": "नलय क भत्त, अलद क भत्त स े________ होती ह।ै",
      "options": [
        "मोटी",
        "छोटी",
        "पतली",
        "बड़ी"
      ],
      "correctIndex": 0,
      "explanation": "सही उत्तर विकल्प (A) अर्थात मोटी है।\n\nयह प्रश्न RRB Group D 31/10/2018 Shift 2 2018 में पूछा गया था।",
      "examName": "RRB Group D 31/10/2018 Shift 2",
      "examYear": "2018"
    },
    {
      "id": "q_570",
      "type": "standard",
      "question": "नम्नलखत म स ेक्या भोजन, काबन डाइऑक्साइड और नाइटोजनयक्ुत अपशष्टा को घुलत रू प म स्थानांतरत करता ह?ै",
      "options": [
        "प्लाज्मा",
        "WBC",
        "RBC",
        "प्लटेलटेस् InstBack to Telegram"
      ],
      "correctIndex": 0,
      "explanation": "सही उत्तर विकल्प (A) अर्थात प्लाज्मा है।\n\nयह प्रश्न RRB Group D 13 /9/2022 Shift 1 2022 में पूछा गया था।",
      "examName": "RRB Group D 13 /9/2022 Shift 1",
      "examYear": "2022"
    },
    {
      "id": "q_571",
      "type": "standard",
      "question": "अधकांश सरीसपृा म ________ ह।ै",
      "options": [
        "चार कक्षीय हृदय",
        "दो कक्षीय हृदय",
        "तीन कक्षीय हृदय",
        "अपूण तीन कक्षीय हृद्य"
      ],
      "correctIndex": 2,
      "explanation": "सही उत्तर विकल्प (C) अर्थात तीन कक्षीय हृदय है।\n\nयह प्रश्न RRB Group D 22 Sept 2018 Shift 2 2018 में पूछा गया था।",
      "examName": "RRB Group D 22 Sept 2018 Shift 2",
      "examYear": "2018"
    },
    {
      "id": "q_572",
      "type": "standard",
      "question": "नम्नलखत म स ेकौन सा कथन मछलया के बारे म सही नह ह?ै",
      "options": [
        "मछलया के हृदय म केवल दो कक्ष होते ह।",
        "मछली के हृदय स ेरक्त एक चक्र म केवल एक बार जाता है।",
        "मछलया म दोहरा परसंचरण होता है।",
        "मछलया के गलफड़ा के माध्यम से रक्त पंप कया जाता ह ैऔर ऑक्सीजन यक्ुत हो जाता है।"
      ],
      "correctIndex": 2,
      "explanation": "सही उत्तर विकल्प (C) अर्थात मछलया म दोहरा परसंचरण होता है। है।\n\nयह प्रश्न RRB NTPC CBT-I : 16 Jan 2021 Shift 2 2021 में पूछा गया था।",
      "examName": "RRB NTPC CBT-I : 16 Jan 2021 Shift 2",
      "examYear": "2021"
    },
    {
      "id": "q_573",
      "type": "standard",
      "question": "द्वशीष पत्ती के ऊपरी और नचले एपडमस के बीच पाए जाने वाले ऊतक को क्या कहते ह?",
      "options": [
        "परसंचरण तंत्र",
        "मेसोफल",
        "उत्तर",
        "गूदा"
      ],
      "correctIndex": 1,
      "explanation": "सही उत्तर विकल्प (B) अर्थात मेसोफल है।\n\nयह प्रश्न RPF SI 2018 : 11 Jan 2019 Shift 2 2018 में पूछा गया था।",
      "examName": "RPF SI 2018 : 11 Jan 2019 Shift 2",
      "examYear": "2018"
    },
    {
      "id": "q_574",
      "type": "standard",
      "question": "मानव रक्त म प्लाज्मा का क्या काय होता ह?ै",
      "options": [
        "यह फेफड़ा से ऑक्सीजन को शरीर के सभी भागा तक पहुंचाता है।",
        "यह ऊतका को ऑक्सीजन यक्ुत रक्त क आपूत बनाए रखता है।",
        "यह भोजन, काबन डाइऑक्साइड और अपशष्ट पदाथा का परवहन करता है।",
        "यह चोट लगन ेपर रक्त का थक्का जमान ेम मदद करता है।"
      ],
      "correctIndex": 2,
      "explanation": "सही उत्तर विकल्प (C) अर्थात यह भोजन, काबन डाइऑक्साइड और अपशष्ट पदाथा का परवहन करता है। है।\n\nयह प्रश्न RRB Level 01 Stage I 23/12/2025 4:30 PM - 6:00 PM 2025 में पूछा गया था।",
      "examName": "RRB Level 01 Stage I 23/12/2025 4:30 PM - 6:00 PM",
      "examYear": "2025"
    },
    {
      "id": "q_575",
      "type": "standard",
      "question": "हृदय चक्र क्या ह?ै",
      "options": [
        "एक स्पंद और एक नाड़ी दर",
        "एक स्वतः ग्राही और एक फुफ्फुस चक्र",
        "हृदय के संकुचन और शथलन का एक चक्र",
        "दोहरा अलद नलय कपाट मुख"
      ],
      "correctIndex": 2,
      "explanation": "सही उत्तर विकल्प (C) अर्थात हृदय के संकुचन और शथलन का एक चक्र है।\n\nयह प्रश्न RRB Group D 2 Nov 2018 Shift 2 2018 में पूछा गया था।",
      "examName": "RRB Group D 2 Nov 2018 Shift 2",
      "examYear": "2018"
    },
    {
      "id": "q_576",
      "type": "standard",
      "question": "धड़कन का क्या कारण होता ह?ै",
      "options": [
        "हृदय म रक्त प्रवाह",
        "धमनया म रक्त प्रवाह",
        "फेफड़ा म रक्त प्रवाह",
        "शराआ म रक्त प्रवाह"
      ],
      "correctIndex": 1,
      "explanation": "सही उत्तर विकल्प (B) अर्थात धमनया म रक्त प्रवाह है।\n\nयह प्रश्न RRB Group D 30 /9/2022 Shift 2 2022 में पूछा गया था।",
      "examName": "RRB Group D 30 /9/2022 Shift 2",
      "examYear": "2022"
    },
    {
      "id": "q_577",
      "type": "standard",
      "question": "रक्त स्कंदन _____________ क सहायता स ेहोता ह।ै",
      "options": [
        "प्लटेलटे कोशकाआ",
        "लाल रक्त कोशकाआ",
        "श्वेत रक्त कोशकाआ",
        "रक्त प्लाज़्मा"
      ],
      "correctIndex": 0,
      "explanation": "सही उत्तर विकल्प (A) अर्थात प्लटेलटे कोशकाआ है।\n\nयह प्रश्न RRB Group D 26 /9/2022 Shift 2 2022 में पूछा गया था।",
      "examName": "RRB Group D 26 /9/2022 Shift 2",
      "examYear": "2022"
    },
    {
      "id": "q_578",
      "type": "standard",
      "question": "मछलया म रक्त परसचंरण के सबंधं म गलत कथन क पहचान कजए।",
      "options": [
        "नलय स ेरक्त केवल क्लोम तक जाता है।",
        "रक्त क्लोम स ेशरीर के बाक हस्सा म जाता है।",
        "शरीर स ेरक्त अलद म प्रवेश करता है।",
        "दो कक्षीय हृदय म दोहरा परसंचरण होता है। Index Youtube"
      ],
      "correctIndex": 3,
      "explanation": "सही उत्तर विकल्प (D) अर्थात दो कक्षीय हृदय म दोहरा परसंचरण होता है। Index Youtube है।\n\nयह प्रश्न RRB Group D 13 /9/2022 Shift 1 2022 में पूछा गया था।",
      "examName": "RRB Group D 13 /9/2022 Shift 1",
      "examYear": "2022"
    },
    {
      "id": "q_579",
      "type": "standard",
      "question": "पल्स ______ क तरंग ह।ै",
      "options": [
        "कुछ समय",
        "लगातार अवध",
        "उच्च अवध",
        "स्पंदन और कंपन"
      ],
      "correctIndex": 0,
      "explanation": "सही उत्तर विकल्प (A) अर्थात कुछ समय है।\n\nयह प्रश्न RRB Group D 28 Sept 2018 Shift 3 2018 में पूछा गया था।",
      "examName": "RRB Group D 28 Sept 2018 Shift 3",
      "examYear": "2018"
    },
    {
      "id": "q_580",
      "type": "standard",
      "question": "कौन सी रक्त कोशकाएँ रक्त के थक्के बनाने और रक्तस्राव को रोकने म मदद करती ह?",
      "options": [
        "लाल रक्त कोशकाएँ",
        "प्लटेलटेस और लाल रक्त कोशकाएँ दोना्",
        "प्लटेलटेस्",
        "श्वेत रक्त कोशकाएँ Solutions — Biology Q514.Solution: सही उत्तर ह ैमछली Explanation: दोहरा परसचंरण वह प्रक्रया ह ैजसम रक्त हृदय स ेदो बार गुजरता है: एक बार फेफड़ा (या गलफड़ा) तक और फर शरीर के बाक हस्सा तक। यह प्रणाली उभयचर, सरीसृप, पक्षया और स्तनधारया म पाइ जाती ह।ै मछलया म एकल परसचंरण होता ह,ै जहा ंरक्त हृदय से केवल एक बार गुजरता ह,ै गलफड़ा स ेहोकर शरीर तक पहुचंता ह ैऔर फर हृदय म वापस आता है। मढक (उभयचर), गरुड़ (पक्षी) और साँप (सरीसपृ) म दोहरा परसचंरण पाया जाता है, हालांक उभयचरा और सरीसपृा म यह अधूरा होता ह।ै इसलए, मछली म दोहरा परसचंरण नह पाया जाता। Important one-liners for upcoming exams: दोहरा परसचंरण कसम नह पाया जाता? मछली →☛ कसम एकल परसचंरण पाया जाता ह?ै मछली →☛ उभयचरा म परसचंरण का प्रकार? अधूरा दोहरा परसचंरण →☛ पक्षया और स्तनधारया म परसचंरण? पणू दोहरा परसचंरण →☛ सरीसपृा म परसचंरण? अधूरा दोहरा परसचंरण →☛ Q515.सही उत्तर: वकल्प 4 — वऑक्सीजनत रुधर दाहन ेनलय स ेफेफड़ा तक पपं कया जाता ह।ै व्याख्या: फुफ्फुसीय परसचंरण वह माग ह ैजो हृदय और फेफड़ा के बीच रुधर के ऑक्सीजनीकरण के लए परवहन करता ह।ै शरीर स ेवऑक्सीजनत रुधर ( काबन डाइऑक्साइड यक्ुत) दाहन ेअलद म लौटता ह,ै दाहन ेनलय फुफ्फुसीय धमनी के माध्यम स ेफेफड़ा तक पपं कया जाता ह।ै फेफड़ा क केशकाआ म, काबन डाइऑक्साइड बाहर वसरत होती ह ैऔर ऑक्सीजन अंदर वसरत होती ह,ै जसस ेरुधर ऑक्सीजनत हो जाता ह।ै वकल्प 4 सही ह ैक्याक यह इस प्रक्रया का सटीक वणन करता ह।ै वकल्प 1 गलत ह ैक्याक वऑक्सीजनत रुधर दाहन ेनलय से पंप होता ह,ै बाए से नह। वकल्प 2 गलत ह ैक्याक फेफड़ा स ेऑक्सीजनत रुधर बाए अलद म जाता ह,ै दाहने म नह। वकल्प 3 गलत ह ैक्याक ऑक्सीजनत रुधर फेफड़ा स ेशरीर म प्रवाहत होता है, शोधन के लए फेफड़ा म नह। परीक्षा के लए अतरक्त तथ्य: • फुफ्फुसीय धमनी एकमात्र धमनी ह ैजो वऑक्सीजनत रुधर ले जाती ह।ै • फुफ्फुसीय शरा एकमात्र शरा ह ैजो ऑक्सीजनत रुधर ल ेजाती ह।ै • ऑक्सीजन वनमय फेफड़ा के कूपकाआ म केशका भत्तया के पार वसरण द्वारा होता है। • दाहन ेनलय क दीवार बाए नलय स ेपतली होती ह क्याक यह रुधर केवल फेफड़ा तक पपं करता ह।ै • व्यवस्थत परसचंरण ऑक्सीजनत रुधर को बाए नलय स ेशरीर के ऊतका तक ल ेजाता है। आगामी परीक्षाआ के लए महत्वपूण एक-पंक्त प्रश्न: कौन-सी धमनी वऑक्सीजनत रुधर ले जाती है? फुफ्फुसीय धमनी →☛ दाहन ेनलय स ेरुधर कहाँ जाता है? फेफड़ा म फुफ्फुसीय धमनी के माध्यम से →☛ फेफड़ा स ेऑक्सीजनत रुधर हृदय म कैस ेप्रवेश करता है? बाए अलद म फुफ्फुसीय →☛ शराआ के माध्यम से कस परसचंरण म फेफड़े शामल होत ेह? फुफ्फुसीय परसचंरण →☛ InstBack to Telegram Important one-liners for upcoming exams: पल्मोनरी सकुलेशन म रक्त को ऑक्सीजन कहा ंमलता ह?ै फेफड़ा म →☛ हृदय के कस भाग म पल्मोनरी शरा रक्त लाती ह?ै बाए आलद म →☛ शरीर क सबस ेबड़ी शरा कौन सी ह?ै वीना कावा (Vena Cava) →☛ पल्मोनरी धमनी कस प्रकार का रक्त ले जाती ह?ै डीऑक्सीजनत रक्त →☛ पोटल शरा कस अंग स ेरक्त ले जाती ह?ै आतं स ेयकृत तक →☛ Q519.Solution: सही उत्तर ह ैप्लेटलेटस् Explanation: रक्त का थक्का जमना एक महत्वपणू प्रक्रया ह ैजो रक्तस्राव को रोकती है। प्लेटलेटस, जन्ह् थ्रोम्बोसाइटस भी कहा जाता ह,ै अस्थ मज्जा म बनने वाली छोटी, रंगहीन कोशकाएँ ह। जब कोइ् रक्त वाहका क्षतग्रस्त होती ह,ै तो प्लेटलेटस सक्रय हो जात ेह और क्षतग्रस्त स्थान पर एकत्रत् होकर एक अस्थायी प्लग बनात ेह। व ेएक रासायनक प्रतक्रया शुरू करत ेह जसम फाइब्रनोजेन फाइब्रन म परवतत हो जाता ह,ै जो एक जाल क तरह काम करता ह ैऔर अधक प्लेटलेटस और् लाल रक्त कणकाआ को फँसाकर स्थायी थक्का बनाता ह।ै लाल रक्त कणकाएँ ऑक्सीजन ले जाती ह, श्वेत रक्त कणकाएँ प्रतरोधक क्षमता म मदद करती ह, लेकन थक्का जमन ेका काय केवल प्लेटलेटस करत ेह।् Important one-liners for upcoming exams: रक्त का थक्का जमान ेवाली कोशकाएँ प्लेटलेटस (थ्रोम्बोसाइटस)्् →☛ प्लेटलेटस का नमाण कहाँ होता ह ै अस्थ मज्जा् →☛ थक्का जमन ेम आवश्यक प्रोटीन फाइब्रनोजने और फाइब्रन →☛ प्लेटलेटस क कमी स ेक्या होता ह ै अत्यधक रक्तस्राव (थ्रोम्बोसाइटोपेनया)् →☛ रक्त म प्लेटलेटस क सामान्य सख्ंया 1.5 लाख स े4.5 लाख प्रत माइक्रोलीटर् →☛ Q520.Solution: सही उत्तर ह ैपेरकाडयल मेम्ब्रेन Explanation: हृदय दो परता वाली एक झल्ली स ेढका होता ह ैजस ेपेरकाडयम कहा जाता ह।ै यह झल्ली हृदय को घरेे रहती ह ैऔर इस ेसरुक्षा प्रदान करती ह।ै बाहरी परत को पाश्वका पेरकाडयम और भीतरी परत को आंत पेरकाडयम कहा जाता ह।ै इन दोना परता के बीच एक द्रव भरा स्थान होता ह ैजसे पेरकाडयल गहुा कहत ेह, जो हृदय के धड़कने के दौरान घषण को कम करता ह।ै पेरकाडयल झल्ली हृदय को अत्यधक फैलने स ेभी रोकती ह।ै अन्य वकल्प जसै ेपल्मोनरी मेम्ब्रेन फेफड़ा से सबंंधत ह। Important one-liners for upcoming exams: हृदय क बाहरी झल्ली पेरकाडयम →☛ पेरकाडयम क परत पाश्वका और आतं →☛ पेरकाडयल गहुा म भरा द्रव पेरकाडयल द्रव →☛ पेरकाडयम का काय सरुक्षा और घषण कम करना →☛ हृदय क झल्ली का नाम पेरकाडयम →☛ Q521.Solution: सही उत्तर ह ैटाइकस्पड Explanation: हृदय म दाए अटयम और दाए वटकल के बीच स्थत वाल्व को टाइकस्पड वाल्व कहा जाता ह।ै इस ेदायाँ अलद-नलय वाल्व भी कहत ेह, जसम तीन पतले पत्रक होत ेह जो पैपलरी मांसपेशया द्वारा कॉड टडनी के माध्यम स ेजड़ुे होत ेह। यह वाल्व रक्त को दाए अटयम स ेदाए वटकल म प्रवाहत होने देता ह ैऔर वापसी को रोकता ह।ै Important one-liners for upcoming exams: बाइकस्पड वाल्व कहाँ स्थत होता ह?ै बाए अटयम और बाए वटकल के बीच →☛ पल्मोनरी वाल्व का काय क्या ह?ै दाए वटकल स ेफुफ्फुस धमनी म रक्त प्रवाह को →☛ नयंत्रत करना महाधमनी वाल्व कहाँ स्थत ह?ै बाए वटकल और महाधमनी के बीच →☛ हृदय म कतन ेवाल्व होत ेह? चार वाल्व →☛ टाइकस्पड वाल्व का दूसरा नाम क्या ह?ै दायाँ अलद-नलय वाल्व →☛ Q522.सही उत्तर: धमनी व्याख्या: परसचंरण तत्रं म तीन मख्ुय प्रकार क रक्त वाहकाएँ होती ह: धमनयाँ , शराएँ , और केशकाएँ InstBack to Telegram इसका काय नलय प्रकंुचन के दौरान बाएँ नलय स ेबाएँ अलद म रक्त के वपरीत प्रवाह को रोकना ह।ै जब यह कपाट ठक स ेबदं नह होता ( मटल कपाट रगजटेशन ), तो नलय के सकंुचन के दौरान रक्त पीछे क ओर बाएँ अलद म प्रवाहत होता ह।ै एसेा इसलए होता ह ैक्याक बाएँ नलय म दबाव बाएँ अलद स ेअधक होता ह ैऔर दोषपणू कपाट उाटन को बंद नह कर पाता। वकल्प 2 गलत ह ैक्याक त्रवलनी कपाट दाएँ नलय स ेदाएँ अलद म वपरीत प्रवाह रोकता ह।ै वकल्प 3 गलत ह ैक्याक ऑक्सीजनत और वऑक्सीजनत रक्त का मश्रण आमतौर पर जन्मजात हृदय दोषा म होता ह,ै अलग कपाट वफलता म नह। वकल्प 4 गलत ह ैक्याक फेफड़ा म रक्त प्रवाह कम होना दाएँ हृदय समस्याआ या फुफ्फुसीय कपाट समस्याआ स ेजुड़ा ह,ै मटल कपाट दोष स ेनह। परीक्षा के लए अतरक्त तथ्य: • मटल कपाट म दो पद (द्ववलनी) होत ेह, जबक त्रवलनी कपाट म तीन पद होत ेह। • कपाट वकारा म स्टेनोसस ( सकंणन) और रगजटेशन ( रसाव) शामल ह। • अधचंद्राकार कपाट ( महाधमनी और फुफ्फुसीय) अनुशथलन के दौरान नलय म वपरीत प्रवाह रोकत ेह। • हृदय ध्वन \"लब-डब\" क्रमशः अलद-नलय कपाट बदं होने (लब) और अधचंद्राकार कपाट बंद होने (डब) स ेमले खाती ह।ै • रुमेटक बखुार वकासशील देशा म मटल कपाट क्षत का एक सामान्य कारण है। आगामी परीक्षाआ के लए महत्वपूण एक-पंक्त प्रश्न: कौन सा कपाट बाएँ नलय स ेबाएँ अलद म वपरीत प्रवाह रोकता है? मटल →☛ (द्ववलनी) कपाट रसत ेहृदय कपाट के लए चकत्सा शब्द क्या है? वाल्वलुर रगजटेशन →☛ त्रवलनी कपाट म कतन ेपद होत ेह? तीन पद →☛ कौन सी हृदय ध्वन एवी कपाट बंद होन ेस ेमेल खाती है? प्रथम हृदय ध्वन (लब) →☛ दाएँ अलद को दाएँ नलय स ेक्या जोड़ता है? त्रवलनी कपाट →☛ Q525.सही उत्तर: वकल्प 1 — शराए नम्न दाब पर रक्त ले जाती ह और रक्त के उल्टे प्रवाह को रोकने के लए वाल्व क आवश्यकता होती ह।ै व्याख्या: शराआ म वाल्व होत ेह जबक धमनया म नह, यह रक्तचाप और प्रवाह दशा के अतंर के कारण ह।ै धमनयाँ हृदय स ेरक्त को उच्च दाब पर ल ेजाती ह जो नलय सकंुचन द्वारा उत्पन्न होता ह,ै जसस ेएक मजबतू एकदशीय प्रवाह बनता ह ैजस ेवाल्व क आवश्यकता नह होती। इसके वपरीत, शराएँ केशकाआ स ेगुजरने के बाद नम्न दाब पर हृदय म रक्त वापस ल ेजाती ह। यह नम्न दाब, गुरुत्वाकषण के प्रभाव (वशेषकर अगंा म) के साथ मलकर, उल्टे प्रवाह क संभावना बढ़ाता ह।ै शराआ म वाल्व फ्लैप जसैी सरंचनाएँ ह जो हृदय क ओर रक्त प्रवाह क अनुमत देने के लए खलुती ह लेकन उल्टे प्रवाह को रोकन ेके लए बदं हो जाती ह। वकल्प 2 गलत ह ैक्याक शराएँ उच्च दाब पर रक्त नह ले जात। वकल्प 3 गलत ह ैक्याक वाल्व क आवश्यकता दाब पर नभर करती ह,ै रक्त के ऑक्सीजनयक्ुत होन ेपर नह (फुफ्फुसीय धमनयाँ बना वाल्व के अशुद्ध रक्त ले जाती ह)। वकल्प 4 गलत ह;ै धमनया का स्थान वाल्व क उपस्थत नधारत नह करता। परीक्षा के लए अतरक्त तथ्य: • शराआ क दीवार धमनया क तलुना म पतली होती ह, जनम कम चकनी पेशी और लोचदार ऊतक होत ेह। • वैरकोज वेन्स तब होती ह जब शरापरक वाल्व अक्षम हो जात ेह, जसस ेरक्त जमाव होता है। • कंकाल पेशी पंप सकंुचन के दौरान शराआ को दबाकर शरापरक वापसी म मदद करता है। • फुफ्फुसीय धमनयाँ अशुद्ध रक्त फेफड़ा म ल ेजाती ह; फुफ्फुसीय शराएँ शुद्ध रक्त हृदय म ले जाती ह। • केशकाआ म वाल्व नह होत ेऔर उनक दीवार केवल एक कोशका मोटी होती ह, जो कुशल वनमय के लए होती ह। आगामी परीक्षाआ के लए महत्वपूण एक-पंक्त प्रश्न: कन रक्त वाहकाआ म वाल्व होत ेह? शराएँ →☛ शराआ म उल्टे प्रवाह को क्या रोकता है? वाल्व →☛ धमनया को वाल्व क आवश्यकता क्या नह होती? उच्च रक्तचाप एकदशीय प्रवाह →☛ बनाए रखता है अधचंद्राकार वाल्व कहाँ पाए जात ेह? हृदय (महाधमनी और फुफ्फुसीय वाल्व) →☛ वाल्व के अलावा शरापरक वापसी म क्या मदद करता है? कंकाल पशेी पपं और श्वसन →☛ पपं InstBack to Telegram व्याख्या: हृदय के नलय म आलद क तलुना म मोटी पशेीय भत्तयाँ होती ह क्याक उन्ह सचंार प्रणाली म रक्त पपं करने के लए उच्च दाब उत्पन्न करने क आवश्यकता होती है। बायाँ नलय क भत्त सबसे मोटी होती ह ैक्याक यह महाधमनी के माध्यम स ेपरूे शरीर म ऑक्सीजनयक्ुत रक्त पपं करता ह,ै जबक दायाँ नलयफुफ्फुसीय धमनी के माध्यम स ेफेफड़ा म वऑक्सीजनत रक्त पपं करता ह।ै वकल्प 1 गलत ह ैक्याक आलद नलय म प्रवेश करने स ेपहले रक्त संग्रहीत करते ह, न क इसके वपरीत। वकल्प 3 गलत ह ैक्याक आलद शरीर और फेफड़ा स ेरक्त प्राप्त करत ेह, नलय नह। वकल्प 4 गलत ह ैक्याक हृदय स्पदं लय अलद-नलय नोड (AVनोड) और अलद-नलय नोड (AVनोड) द्वारा नयंत्रत होती ह,ै न क नलय भत्त क मोटाइ द्वारा। परीक्षा के लए अतरक्त तथ्य: • बायाँ नलय भत्त लगभग 1.3–1.5 समेी मोटी होती ह,ै जबक दायाँ नलय भत्त लगभग 0.3– 0.5 समेी मोटी होती ह।ै • आलद क पतली भत्तया ँहोती ह क्याक व ेकेवल कम दूरी पर नलय म रक्त पंप करते ह। • अंतर-नलय पट बाएँ और दाएँ नलय को अलग करता ह।ै • नलय सकंुचन को प्रकंुचन कहा जाता ह,ै और शथलन को अनुशथलन कहा जाता ह।ै • उच्च रक्तचाप ( हाइपरटशन ) नलय भत्त मोटाइ ( नलय अतवृद्ध ) का कारण बन सकता ह।ै आगामी परीक्षाआ के लए महत्वपूण एक-पंक्तया:ँ कस हृदय कक्ष म सबस ेमोटी पेशीय भत्त होती है? बायाँ नलय →☛ नलय का काय क्या है? धमनया म रक्त पपं करना →☛ कौन सा नलय फेफड़ा म रक्त पंप करता है? दायाँ नलय →☛ हृदय स्पंद लय को क्या नयंत्रत करता है? अलद-नलय नोड ( SA नोड) →☛ बाएँ और दाएँ नलय को क्या अलग करता है? अतंर-नलय पट →☛ Q529.Correct Answer: बड़ी आतं Explanation: परसचंरण तत्रं शरीर म रक्त, पोषक तत्व, गैसा और अपशष्ट उत्पादा के परवहन के लए जम्मेदार ह।ै इसम हृदय ( एक मांसपशेीय पपं), रक्त वाहकाए ( धमनयां, शराए और केशकाए) और रक्त ( एक तरल सयंोजी ऊतक) शामल ह। बड़ी आंतपाचन तत्रं का हस्सा ह,ै परसचंरण तत्रं का नह। यह अवशोषत भोजन स ेपानी और इलेक्टोलाइटस को अवशोषत करके मल बनाती है। इसलए,् वकल्प 1 सही ह ैक्याक यह परसचंरण तत्रं का भाग नह ह।ै वकल्प 2 ( रक्त) एक घटक है, वकल्प 3 ( हृदय) कद्रीय अगं ह,ै और वकल्प 4 ( धमनया)ं रक्त वाहकाए ह जो हृदय से रक्त ले जाती ह। Key Concept / Process: Process/Law: रक्त परसचंरण - पदाथा के परवहन के लए हृदय और रक्त वाहकाआ के माध्यम स ेरक्त क नरंतर गत। Organ/System involved: हृदय, रक्त वाहकाए (धमनया,ं शराए, केशकाए) / परसचंरण तत्रं Scientific name if applicable: लाग ूनह Important values if applicable: सामान्य मानव हृदय गत: 60-100 प्रत मनट; रक्त क मात्रा: वयस्का म ~5 लीटर Extra Facts for Exam: • मानव परसचंरण तत्रं एक बंद प्रणाली ह ैजहा ंरक्त वाहकाआ के भीतर बहता ह।ै • धमनयां ऑक्सीजनयक्ुत रक्त ल ेजाती ह (फुफ्फुसीय धमनी को छोड़कर) और इनक दीवार मोटी और लचीली होती ह। • शराए अशुद्ध रक्त ल ेजाती ह (फुफ्फुसीय शरा को छोड़कर) और इनम वाल्व होत ेह जो रक्त के पीछे क ओर बहने को रोकत ेह। • केशकाए सबस ेछोटी रक्त वाहकाए ह जहां गैसा और पोषक तत्वा का आदान-प्रदान होता है। • हृदय म चार कक्ष होत ेह: दो अलद (प्राप्त करने वाले) और दो नलय (पपं करन ेवाले)। Important One-liners for Upcoming Exams: परसचंरण तत्रं म कौन सा अंग रक्त पंप करता है? हृदय →☛ धमनयां आमतौर पर कस प्रकार का रक्त ले जाती ह? ऑक्सीजनयक्ुत रक्त →☛ (फुफ्फुसीय धमनी को छोड़कर) परसचंरण तत्रं म गसै वनमय कहाँ होता है? केशकाए →☛ कस रक्त वाहका म वाल्व होत ेह? शराए →☛ परसचंरण तत्रं का तरल घटक क्या है? रक्त →☛ InstBack to Telegram मूत्राशय मत्रूत्याग क इच्छा को टगर करने स ेपहले लगभग 400-600 मलीलीटर मूत्र संग्रहीत कर सकता ह।ै • नफ्रेॉन वक्ृक म कायात्मक इकाइयाँ ह जो मत्रू बनान ेके लए रक्त को छानती ह। • मूत्रमाग वह नलका ह ैजो मत्रूत्याग के दौरान मत्रू को मत्रूाशय स ेशरीर के बाहर ले जाती है। • वृक्क धमनयाँ वक्ृक को रक्त क आपूत करती ह, जबक वृक्क शराएँ छन ेहुए रक्त को वक्ृक स ेदूर ले जाती ह। • मत्रू सरंचना म आमतौर पर पानी ( 95%), यूरया, लवण और अन्य अपशष्ट उत्पाद शामल होते ह। आगामी परीक्षाआ के लए महत्वपूण एक-पंक्त प्रश्न: कौन सी सरंचना मूत्र को वृक्क स ेमूत्राशय तक ले जाती है? गवीनी →☛ वृक्क क कायात्मक इकाइ क्या है? नेफ्रॉन →☛ कौन सी नलका मूत्र को शरीर स ेबाहर ले जाती है? मत्रूमाग →☛ मूत्र म मुख्य रूप स ेकौन सा अपशष्ट उत्पाद उत्सजत होता है? यूरया →☛ मनष्ुय म कतनी गवीनयाँ होती ह? दो (प्रत्यके वक्ृक स ेएक) →☛ Q533.Solution: सही उत्तर ह ैचार कक्षीय हृदय Explanation: स्तनधारी जतंआु का हृदय चार कक्षीय होता ह,ै जसम दो अलद (दायां और बायां) तथा दो नलय (दायां और बाया)ं होत ेह। यह सरंचना ऑक्सीजनत और अऑक्सीजनत रक्त को पणूतः पथृक रखती ह,ै जसस ेकुशल ऑक्सीजन परवहन सभंव होता ह।ै चार कक्षीय हृदय स्तनधारया और पक्षया म पाया जाता ह,ै जो उच्च चयापचय दर और गम रक्त (एडोथमक) होन ेस ेसंबंधत है। सरीसपृा म तीन कक्षीय, मछलया म दो कक्षीय हृदय होता ह।ै Important one-liners for upcoming exams: स्तनधारया म हृदय कतन ेकक्षा का होता ह?ै चार कक्षीय →☛ चार कक्षीय हृदय कन वगा म पाया जाता ह?ै स्तनधारी और पक्षी →☛ सरीसपृा के हृदय म कतन ेकक्ष होत ेह? तीन कक्षीय (दो अलद, एक नलय) →☛ मछलया का हृदय कतन ेकक्षीय होता ह?ै दो कक्षीय (एक अलद, एक नलय) →☛ मानव हृदय म कतन ेकक्ष होत ेह? चार कक्षीय →☛ Q534.Solution: सही उत्तर ह ैउच्च रक्तचाप नसा के सकंुचन के कारण होता है Explanation: उच्च रक्तचाप मख्ुयतः धमनया के सकंुचन स ेहोता ह,ै न क नसा के। धमनया क दीवारा पर दबाव बढ़न ेस ेयह स्थत उत्पन्न होती ह।ै प्लेटलेटस रक्त का थक्का जमाने म मदद करत ेह, जो घाव भरने् म सहायक ह।ै लसीका को ऊतक द्रव भी कहा जाता ह,ै क्याक यह कोशकाआ के बीच के द्रव से बनता ह ैऔर लसीका तत्रं म प्रवाहत होता ह।ै केशकाए मलकर शराए बनाती ह, जो रक्त को हृदय क ओर ले जाती ह। अतः वकल्प 1 गलत ह।ै Important one-liners for upcoming exams: उच्च रक्तचाप का मुख्य कारण धमनया का सकंुचन →☛ रक्त का थक्का जमान ेवाला घटक प्लेटलेटस् →☛ लसीका का अन्य नाम ऊतक द्रव →☛ केशकाआ के मलन ेस ेबनन ेवाली रक्तवाहका शरा →☛ परसचंरण तत्रं म रक्त को हृदय तक ले जान ेवाली वाहका शरा →☛ Q535.Solution: सही उत्तर ह ैरक्त नलय म प्रवेश करता ह।ै Explanation: हृदय चक्र म अनुशथलन (डायस्टोल) वह अवस्था ह ैजब हृदय क मांसपेशयाँ शथल होती ह और रक्त हृदय के कक्षा म भरता ह।ै इस समय अलद और नलय दोना शथल होत ेह। अलदा स ेरक्त नलया म प्रवेश करता ह।ै फेफड़ा म रक्त प्रवेश फुफ्फुसीय धमनी के माध्यम स ेसस्टोल म होता ह।ै नलय स ेरक्त बाहर नकलना और महाधमनी म प्रवेश भी सस्टोल के दौरान होता है। इसलए अनुशथलन म केवल रक्त नलय म प्रवेश होता ह।ै Important one-liners for upcoming exams: हृदय चक्र म डायस्टोल क्या ह?ै हृदय क मांसपेशया का शथलन और रक्त भरन ेक →☛ अवस्था डायस्टोल के दौरान हृदय कक्ष कैस ेहोत ेह? अलद और नलय दोना शथल →☛ डायस्टोल म क्या घटत होता ह?ै रक्त नलय म प्रवेश करता है →☛ InstBack to Telegram Explanation: मढक का हृदय तीन कक्षीय होता ह,ै जसम दो अटरया और एक नलय होता ह।ै यह उभयचर वग का जीव ह।ै चड़या का हृदय चार कक्षीय (दो अटरया, दो नलय) होता ह,ै जो पणू रूप से ऑक्सीजनत और अ◌ॉक्सीजनत रक्त को अलग रखता ह।ै मछली का हृदय दो कक्षीय (एक अटरया, एक नलय) होता ह,ै जसम रक्त का एक ही चक्र होता ह।ै मानव का हृदय भी चार कक्षीय होता ह,ै जो दोहरे रक्त परसचंरण के लए अनुकूलत ह।ै मढक के तीन कक्षीय हृदय म ऑक्सीजनत और अ◌ॉक्सीजनत रक्त का कुछ मश्रण होता ह,ै जो उभयचरा क आवश्यकताआ के लए उपयक्ुत ह।ै Important one-liners for upcoming exams: कस वग के जीवा का हृदय दो कक्षीय होता ह?ै मछली →☛ उभयचरा के हृदय म कतन ेकक्ष होत ेह? तीन (दो अटरया, एक नलय) →☛ मनष्ुय के हृदय म कक्षा क सख्ंया कतनी ह?ै चार →☛ पक्षया का हृदय कैसा होता ह?ै चार कक्षीय →☛ मढक के हृदय म रक्त मश्रण क्या होता ह?ै एक नलय के कारण →☛ Q539.Solution: सही उत्तर ह ैमानव ह्रदय खुले हुए हाथ के आकार का होता है Explanation: मानव हृदय लगभग एक बदं मुी के आकार का होता ह,ै न क खलुे हाथ के। यह एक मांसपेशीय अगं ह ैजो रक्त को पपं करता ह।ै धमनया म रक्त उच्च दाब पर प्रवाहत होता ह,ै क्याक वे हृदय से रक्त को दूर ले जाती ह और इनक दीवार मोटी होती ह। रक्त का तरल घटक प्लाज्मा होता ह,ै जसम पानी, प्रोटीन और अन्य पदाथ होत ेह। रक्त शरीर के वजन का लगभग 7-8% बनाता ह,ै जो एक सामान्य व्यक्त म लगभग 5-6 लीटर होता ह।ै इस प्रकार, केवल दूसरा वकल्प गलत है। Important one-liners for upcoming exams: मानव हृदय का आकार कैसा होता ह?ै बदं मुी के बराबर →☛ रक्त का तरल भाग क्या कहलाता ह?ै प्लाज्मा →☛ धमनया म रक्त का दाब कैसा होता ह?ै उच्च दाब →☛ शरीर के वजन म रक्त का प्रतशत कतना होता ह?ै 7-8% →☛ हृदय कस प्रकार का अंग ह?ै मांसपशेीय पपं →☛ Q540.Solution: सही उत्तर ह ैप्लेटलेटस् Explanation: प्लेटलेटस, जन्ह थ्रॉम्बोसाइटस भी कहा जाता ह,ै रक्त के छोटे कोशकय टुकड़े ह जो अस्थ मज्जा्् म बनत ेह। य ेपरूे शरीर म रक्तप्रवाह के साथ घमूत ेह और चोट लगन ेपर रक्त का थक्का बनान ेम मदद करत ेह। चोट के स्थान पर, प्लेटलेटस सक्रय हो जात ेह, एक-दूसरे स ेचपकत ेह और फाइब्रन् के साथ मलकर एक प्लग बनात ेह जो रक्तस्राव रोकता ह।ै यह प्रक्रया हेमोस्टेसस कहलाती है। इसके वपरीत, श्वेत रक्त कणकाए प्रतरक्षा प्रणाली का हस्सा ह, लाल रक्त कणकाए ऑक्सीजन परवहन करती ह, और प्लाज्मा तरल घटक ह।ै Important one-liners for upcoming exams: प्लेटलेटस क कमी स ेकौन सा रोग होता ह?ै थ्रॉम्बोसाइटोपेनया् →☛ प्लेटलेटस क सामान्य सख्ंया कतनी होती ह?ै 1.5 स े4.5 लाख प्रत माइक्रोलीटर् →☛ रक्त का थक्का बनान ेम कौन सा प्रोटीन मदद करता ह?ै फाइब्रन →☛ प्लेटलेटस कहाँ बनत ेह? अस्थ मज्जा् →☛ प्लेटलेटस का जीवनकाल कतना होता ह?ै 7-10 दन् →☛ Q541.Solution: सही उत्तर ह ैधमनी Explanation: धमनया ँव ेरक्त वाहकाएँ ह जो हृदय स ेरक्त को शरीर के वभन्न अगंा तक ले जाती ह। य ेमोटी और लचीली दीवारा वाली होती ह ताक हृदय द्वारा उत्पन्न उच्च दबाव को सहन कर सक। महाधमनी सबस ेबड़ी धमनी ह,ै जो हृदय के बाएँ नलय स ेनकलती ह।ै धमनया ँऑक्सीजन युक्त रक्त (फुफ्फुसीय धमनी को छोड़कर) ल ेजाती ह। शराएँ रक्त को हृदय क ओर लौटाती ह, जबक केशकाएँ अगंा तक पोषक तत्व पहुचँाती ह। Important one-liners for upcoming exams: सबस ेबड़ी धमनी कौन-सी ह?ै महाधमनी →☛ धमनया क दीवार कैसी होती ह? मोटी और लचीली →☛ फुफ्फुसीय धमनी क्या ले जाती ह?ै ऑक्सीजन-रहत रक्त →☛ InstBack to Telegram आगामी परीक्षाआ के लए महत्वपूण एक-पंक्त प्रश्न: ☛प्रकाश संषेण के लए कौन सा वणक आवश्यक है? क्लोरोफल → ☛प्रकाश संषेण के लए कच्चे पदाथ क्या ह? काबन डाइऑक्साइड और जल → ☛पादप कोशकाआ म प्रकाश संषेण कहाँ होता है? क्लोरोप्लास्ट → ☛प्रकाश संषेण का प्राथमक उत्पाद क्या है? ग्लूकोज → ☛प्रकाश संषेण के दौरान कौन सी गसै मुक्त होती है? ऑक्सीजन → Q545.Solution: सही उत्तर ह ै2, 3, 4 और 5 पदा पर Explanation: हृदय म चार वाल्व होत ेह जो रक्त प्रवाह को एकदशीय बनाए रखत ेह। चत्र म स्थान 2 और 3 पर एटयोवटीकुलर वाल्व (माइटल एव ंटाइकस्पड) होत ेह, जो अलदा स ेनलया म रक्त प्रवाह नयंत्रत करत ेह। स्थान 4 और 5 पर समेीलुनर वाल्व (महाधमनी एवं फुफ्फुसीय) नलया स ेबाहर रक्त प्रवाह रोकत ेह। स्थान 1 और 6 पर कोइ वाल्व नह होता; य ेमहाधमनी एवं फुफ्फुसीय शरा जसैी मख्ुय वाहकाआ के मखु ह। अतः सही स्थान 2, 3, 4 और 5 ह। Important one-liners for upcoming exams: हृदय म कतन ेवाल्व होत ेह? चार →☛ बाए अलद व नलय के बीच कौन सा वाल्व ह?ै माइटल वाल्व →☛ दाए अलद व नलय के बीच कौन सा वाल्व ह?ै टाइकस्पड वाल्व →☛ महाधमनी के आधार पर कौन सा वाल्व ह?ै एओटक समेीलुनर वाल्व →☛ फुफ्फुसीय धमनी के आधार पर कौन सा वाल्व ह?ै पल्मोनरी समेीलुनर वाल्व →☛ Q546.सही उत्तर: बायाँ आलद व्याख्या: मानव परसचंरण तत्रं म, फेफड़ा स ेऑक्सीजन यक्ुत रक्त फुफ्फुसीय शराआ के माध्यम स ेहृदय म वापस आता ह।ै य ेशराएँ फेफड़ा स ेऑक्सीजन यक्ुत रक्त को हृदय के बाएँ आलद म ल ेजाती ह। बाएँ आलद स,े रक्त बाएँ नलय म प्रवाहत होता ह,ै जो इस ेमहाधमनी के माध्यम स ेशरीर के बाक हस्सा म पपं करता ह।ै वकल्प 4 ( बाया ँआलद) सही ह ैक्याक यह वह कक्ष है जो सीधे फुफ्फुसीय शराआ स ेऑक्सीजन यक्ुत रक्त प्राप्त करता ह।ै वकल्प 1 ( फुफ्फुसीय धमनया)ँ गलत ह ैक्याक व ेदाएँ नलय स ेफेफड़ा तक वऑक्सीजनत रक्त ल ेजाती ह। वकल्प 2 ( बायाँ नलय) गलत ह ैक्याक यह बाएँ आलद स ेरक्त प्राप्त करता ह,ै सीधे फेफड़ा से नह। वकल्प 3 ( फुफ्फुसीय शराएँ) गलत ह ैक्याक व ेवे रक्त वाहकाएँ ह जो रक्त को बाएँ आलद म लाती ह, कक्ष स्वय ंनह। परीक्षा के लए अतरक्त तथ्य: • मानव हृदय म चार कक्ष होत ेह: दो आलद (दाया ँऔर बाया)ँ और दो नलय (दायाँ और बायाँ) • फुफ्फुसीय धमनयाँ एकमात्र धमनया ँह जो वऑक्सीजनत रक्त ल ेजाती ह • फुफ्फुसीय शराएँ एकमात्र शराएँ ह जो ऑक्सीजन यक्ुत रक्त ल ेजाती ह • दायाँ आलद शरीर स ेवऑक्सीजनत रक्त श्रेष्ठ और अधो महाशरा के माध्यम स ेप्राप्त करता ह ै• बायाँ नलय क मांसपशेीय दीवार सबस ेमोटी होती ह ैताक यह परूे शरीर म रक्त पंप कर सके आगामी परीक्षाआ के लए महत्वपूण एक-पंक्त प्रश्न: हृदय का कौन सा कक्ष फेफड़ा स ेऑक्सीजन युक्त रक्त प्राप्त करता है? बायाँ आलद →☛ कौन सी रक्त वाहकाएँ फेफड़ा स ेहृदय तक ऑक्सीजन युक्त रक्त ले जाती ह? →☛ फुफ्फुसीय शराएँ कौन सी एकमात्र धमनयाँ वऑक्सीजनत रक्त ले जाती ह? फुफ्फुसीय धमनयाँ →☛ कौन सा कक्ष शरीर म ऑक्सीजन युक्त रक्त पंप करता है? बायाँ नलय →☛ हृदय स ेफेफड़ा तक रक्त के माग को क्या कहत ेह? फुफ्फुसीय परसचंरण →☛ Q547.Solution: सही उत्तर ह ैशरीर का तापमान स्थर रखन ेम सहायता करन ेके लए Explanation: मनुष्य और कइ स्तनधारया का हृदय चार कक्षा म वभाजत होता ह ैजो ऑक्सीजन युक्त और ऑक्सीजन रहत रक्त को परूी तरह अलग रखता ह।ै यह पथृक्करण कुशल दोहरा परसचंरण सुनश्चत करता ह ैजसस ेऑक्सीजन यक्ुत रक्त शरीर के वभन्न भागा को अधक कुशलता से ऑक्सीजन पहुचंा पाता ह।ै यह उच्च चयापचय दर को बनाए रखने म मदद करता ह ैजो गम रक्त वाले प्राणया (एडोथम) के लए आवश्यक ह।ै गम रक्त वाल ेप्राणया को शरीर का स्थर तापमान बनाए रखने के लए अधक ऑक्सीजन क आवश्यकता होती ह।ै रक्त का पूण पृथक्करण अधकतम ऑक्सीजन वतरण सुनश्चत करता ह ैजो शरीर के तापमान को स्थर रखने म सहायक InstBack to Telegram Explanation: मछलया का हृदय दो कक्षीय होता ह,ै जसम एक अलद (auricle) और एक नलय (ventricle) होता ह।ै यह सबस ेसरल हृदय सरंचना ह ैजो कशेरुकया म पाइ जाती है। इसम शरस्थ (sinus venosus) और महाधमनी शंकु (conus arteriosus) भी जड़ु ेहोत ेह। यह केवल ऑक्सीजन-रहत रक्त को पपं करता ह,ै क्याक मछलया का परसचंरण तत्रं एकल- परसचंरण (single circulation) होता ह।ै रक्त गलफड़ा म ऑक्सीजनत होकर सीधे शरीर म पहुचँता ह।ै Important one-liners for upcoming exams: द्वपाद (amphibians) का हृदय कतन ेकक्षीय होता ह?ै तीन कक्षीय (दो अलद, एक →☛ नलय) सरीसपृा (reptiles) म हृदय क सरंचना कैसी होती ह?ै तीन कक्षीय, मगरमच्छ को →☛ छोड़कर पक्षया और स्तनधारया का हृदय कतन ेकक्षीय होता ह?ै चार कक्षीय →☛ मछलया म रक्त परसचंरण कस प्रकार का होता ह?ै एकल परसचंरण (single →☛ circulation) मछली के हृदय म कौन-स ेभाग होत ेह? अलद, नलय, शरस्थ और महाधमनी शंकु →☛ Q551.सही उत्तर: वकल्प 3 — रक्त सवंेदी अगंो म सहायता करता ह।ै व्याख्या: परसचंरण तत्रं, जसम मख्ुय रूप स ेहृदय , रक्त वाहकाएँ और रक्त शामल ह, परवहन, नयमन और सरुक्षा के लए जम्मदेार ह।ै रक्त कइ महत्वपणू काय करता ह:ै यह फेफड़ा स ेऊतका तक लाल रक्त कोशकाआ (RBCs) म हीमोग्लोबन के माध्यम स ेऑक्सीजन का परवहन करता है और ऊतका स ेकाबन डाइऑक्साइड को फेफड़ा तक नष्कासन के लए ले जाता ह।ै यह श्वेत रक्त कोशकाआ (WBCs) और प्रतरक्षी पदाथा के माध्यम स ेरोगा स ेसरुक्षा भी प्रदान करता है, और प्लेटलेटस के माध्यम स ेथक्का जमाने म सहायता करता ह।ै हालाँक, सवंेदी अंगो ( जसै ेदृष्ट,् श्रवण, स्पश) का प्रसस्ंकरण तंत्रका तत्रं द्वारा कया जाता ह,ै वशेष रूप स ेसवंेदी न्यरूॉन्स और ग्राही कोशकाआ द्वारा, रक्त द्वारा नह। इस प्रकार, कथन 3 गलत है। कथन 1, 2 और 4 सही ह क्याक व ेरक्त क भूमकाआ को प्रतरक्षा, ऑक्सीजन परवहन और काबन डाइऑक्साइड नष्कासन म सटीक रूप स ेवणत करत ेह। परीक्षा के लए अतरक्त तथ्य: • रक्त म प्लाज्मा (55%), लाल रक्त कोशकाएँ (RBCs, 45%), श्वेत रक्त कोशकाएँ (WBCs) और प्लेटलेटस शामल ह। •् लाल रक्त कोशकाआ म हीमोग्लोबन फेफड़ा म ऑक्सीजन को बांधता ह ैऔर ऊतका म मक्ुत करता ह;ै यह कुछ काबन डाइऑक्साइड भी ल ेजाता ह।ै • श्वेत रक्त कोशकाएँ ( ल्यकूोसाइटस) म न्यटूोफल, लम्फोसाइटस और मोनोसाइटस शामल ह,््् जो सक्रंमण स ेलड़ती ह। • हृदय म चार कक्ष होत ेह: दो अलद (रक्त प्राप्त करत ेह) और दो नलय (रक्त पंप करते ह)। • रक्त समहूा को लाल रक्त कोशकाआ क सतह पर प्रतजना के आधार पर ABO और Rh प्रणालया द्वारा वगकृत कया जाता ह।ै आगामी परीक्षाआ के लए महत्वपूण एक-पंक्त प्रश्न: रक्त का कौन सा घटक ऑक्सीजन परवहन के लए जम्मेदार है? लाल रक्त कोशकाएँ →☛ ( RBCs) जनम हीमोग्लोबन होता ह।ै मानव रक्त का सामान्यpHसीमा क्या है? 7.35 स े7.45 ( थोड़ा क्षारीय)। →☛ कौन सी रक्त कोशकाएँ प्रतरक्षा प्रतक्रयाआ म शामल ह? श्वेत रक्त कोशकाएँ →☛ (ल्यकूोसाइटस)।् रक्त म प्लेटलेटस का काय क्या है? रक्त का थक्का जमना (हमेोस्टेसस)।् →☛ रक्त द्वारा ऊतका स ेफेफड़ा तक कौन सी गसै का परवहन कया जाता है? काबन →☛ डाइऑक्साइड ( CO) । ₂ Q552.Solution: सही उत्तर ह ैबायाँ अलन्द Explanation: फुफ्फुस शरा (pulmonary vein) फेफड़ा स ेऑक्सीजन यक्ुत रक्त को हृदय तक लाती है। यह रक्त सीधे बाएँ अलन्द (left atrium) म प्रवेश करता ह।ै बाएँ अलन्द स ेरक्त बाएँ नलय (left ventricle) म जाता ह,ै जहाँ स ेइस ेपरूे शरीर म पपं कया जाता ह।ै दाएँ अलन्द म डीऑक्सीजनेटेड रक्त आता ह,ै जबक दाएँ नलय फेफड़ा म रक्त भेजता है। फुफ्फुस शरा कसी नलय या दाएँ अलन्द स ेनह जड़ुती। InstBack to Telegram कोशका आकार के आधार पर, उपकला ऊतका को शल्क, घनाकार या स्तभंाकार के रूप म वगकृत कया जाता ह।ै • सरल उपकला एकल-परत वाली होती ह ैजो अवशोषण/स्राव के लए होती ह,ै जबक स्तरत उपकला बहु-परत वाली होती ह ैजो सरुक्षा के लए होती ह।ै • श्वसन तत्रं म पक्ष्माभी उपकला ष्ेमा और फंस ेकणा को हलाने म मदद करती ह।ै • ग्रंथल उपकला ग्रंथया का नमाण करती ह ैजो हामान, एजाइम या पसीना स्रावत करती ह। आगामी परीक्षाआ के लए महत्वपूण एक-पंक्त प्रश्न: रक्त वाहकाआ क अस्तर कौन सा ऊतक बनाता है? सरल शल्क उपकला →☛ स्तरत शल्क उपकला का मुख्य काय क्या है? यांत्रक चोट के खलाफ सरुक्षा →☛ वृक्क नलकाआ म कौन सा उपकला ऊतक पाया जाता है? घनाकार उपकला →☛ कौन सा उपकला ऊतक तीव्र वसरण क अनमुत देता है? सरल शल्क उपकला →☛ कौन सा ऊतक अंतरकोशकय आधात्री का अभाव रखता है? उपकला ऊतक →☛ Q556.सही उत्तर: वक्ृक धमनी व्याख्या: परसचंरण तत्रं धमनया और शराआ के माध्यम स ेपरूे शरीर म रक्त का परवहन करता है। धमनयाँ हृदय स ेऑक्सीजनयक्ुत रक्त को वभन्न अगंा तक ले जाती ह, जबक शराएँ डीऑक्सीजनेटेड रक्त को हृदय म वापस ल ेजाती ह। वृक्क धमनी वशेष रूप स ेउदर महाधमनी से नकलती ह ैऔर हृदय स ेगुदा तक छनन के लए ऑक्सीजन-यक्ुत रक्त पहुचँाती है। इसके वपरीत, वृक्क शरा छने हुए, डीऑक्सीजनेटेड रक्त को गुदा स ेहृदय म अधोमहाशरा के माध्यम स ेवापस ले जाती ह।ै महाशरा एक प्रमखु शरा ह ैजो शरीर स ेरक्त को हृदय म वापस ल ेजाती ह,ै गुदा तक नह। हृदय धमनी हृदय क मांसपेशया को रक्त क आपूत करती ह,ै गुदा को नह। इसलए, केवल वक्ृक धमनी ही सही ढंग स ेउस वाहका का वणन करती ह ैजो हृदय स ेगुदा तक रक्त ले जाती है। परीक्षा के लए अतरक्त तथ्य: • मानव परसचंरण तत्रं एक बदं, दो-लूप प्रणाली ह ैजसम फुफ्फुसीय और प्रणालीगत सकट होते ह। • धमनया म मोटी, मांसल दीवार होती ह ताक हृदय के सकंुचन स ेउच्च दबाव को सहन कर सक। • शराआ म पतली दीवार होती ह और रक्त के प्रतवाह को रोकने के लए वाल्व होत ेह। • वृक्क धमनी छनन के लए गुदा को प्रत मनट लगभग 1.2 लीटर रक्त पहुचँाती है। • छना हुआ रक्त वृक्क शरा के माध्यम स ेअधोमहाशरा म वापस आता ह।ै आगामी परीक्षाआ के लए महत्वपूण एक-पंक्तया:ँ कौन सी वाहका गदुा तक ऑक्सीजनयुक्त रक्त ले जाती है? वक्ृक धमनी →☛ गदुा स ेहृदय तक डीऑक्सीजनटेेड रक्त क्या ले जाती है? वक्ृक शरा →☛ मानव शरीर क सबस ेबड़ी धमनी कौन सी है? महाधमनी →☛ कौन सी शरा नचले शरीर स ेहृदय तक रक्त ले जाती है? अधोमहाशरा →☛ कौन सी धमनी हृदय क मांसपेशया को रक्त क आपूत करती है? हृदय धमनी →☛ Q557.सही उत्तर: हमारे शरीर म सचंलन व्याख्या: कंकाल पेशयाँ एेच्छक पेशया ँह जो कण्डराआ के माध्यम स ेहया स ेजड़ुी होती ह, जो कंकाल- पेशी तत्रं बनाती ह। इनका प्राथमक काय तंत्रका सकंेता के प्रत सकुड़ने और शथल होने से सचंलन सगुम बनाना ह,ै जो गत, मद्रुा बनाए रखन ेऔर सक्ष्ूम मोटर कौशल को सक्षम करता है। वकल्प 1 सही ह ैक्याक कंकाल पेशयाँ हया स ेअपने जड़ुाव के माध्यम स ेसीधे शरीर क गतया का कारण बनती ह। वकल्प 2 ( परसचंरण) गलत ह ैक्याक यह मख्ुय रूप से हृदय ( हृदय पशेी) और रक्त वाहकाआ का काय ह।ै वकल्प 3 ( उत्सजन) गलत ह ैक्याक यह वृक्का , त्वचा, फेफड़ा और यकृत द्वारा कया जाता ह।ै वकल्प 4 ( श्वसन) गलत ह ैक्याक इसम फेफड़े और डायाफ्राम (श्वास के लए एक कंकाल पशेी, लेकन सभी कंकाल पेशया का मख्ुय काय नह) शामल ह। परीक्षा के लए अतरक्त तथ्य: • कंकाल पेशया ँरेखत होती ह और कायक तंत्रका तत्रं के माध्यम स ेएेच्छक नयत्रंण म होती ह। • वे एक औसत वयस्क मानव म कुल शरीर के वजन का लगभग 40% बनाती ह। • कण्डराएँ पेशया को हया स ेजोड़ती ह, जबक स्नायु हया को अन्य हया स ेजोड़त ेह। • अवायवीय श्वसन स ेलैक्टक अम्ल के सचंय के कारण पशेी थकान होती है। • सबस ेबड़ी कंकाल पशेी ग्लूटयस मैक्समस ( नतबं पशेी) ह,ै और सबस ेछोटी मध्य कान म स्टेपीडयस ह।ै आगामी परीक्षाआ के लए महत्वपूण एक-पंक्तया:ँ InstBack to Telegram भागा (फेफड़ा को छोड़कर) तक ल ेजाती ह।ै इसम ऑक्सीजन यक्ुत रक्त प्रवाहत होता है। फुफ्फुसीय धमनी रक्त को हृदय स ेफेफड़ा तक ल ेजाती ह,ै जबक फुफ्फुसीय शरा रक्त को फेफड़ा स ेहृदय तक लाती ह।ै महाशरा ऑक्सीजन रहत रक्त को शरीर स ेहृदय तक वापस लाती है। इस प्रकार, महाधमनी ही एकमात्र वाहका ह ैजो फेफड़ा को छोड़कर शरीर के बाक अंगा तक रक्त पहुचँाती ह।ै Important one-liners for upcoming exams: सबस ेबड़ी धमनी कौन सी ह?ै महाधमनी →☛ महाधमनी कहाँ स ेशुरू होती ह?ै बाए नलय से →☛ फुफ्फुसीय धमनी क्या ले जाती ह?ै ऑक्सीजन रहत रक्त फेफड़ा तक →☛ महाशरा क्या ले जाती ह?ै ऑक्सीजन रहत रक्त हृदय तक →☛ कस वाहका म ऑक्सीजन युक्त रक्त होता ह?ै महाधमनी →☛ Q562.Solution: सही उत्तर ह ैरक्त कम दबाव म बहता ह,ै झटके के साथ और उनम तजे होता ह।ै Explanation: सवंहन तत्रं म रक्त उच्च दबाव म बहता ह,ै वशेषकर धमनया म। यह झटके के साथ नह बल्क सतत प्रवाह के रूप म बहता ह।ै रक्त एक तरल ऊतक ह ैजो परूे शरीर म पोषक तत्व, ऑक्सीजन और अपशष्ट पदाथा का परवहन करता ह।ै मानव शरीर के कुल वजन का लगभग 7-8% हस्सा रक्त का होता ह।ै औसत वयस्क म लगभग 5-6 लीटर रक्त होता ह।ै रक्त को प्राचीन काल से 'जीवन क नदी' कहा जाता ह ैक्याक यह जीवन के लए आवश्यक ह।ै मानव लाल रक्त कोशकाआ (आरबीसी) का जीवनकाल लगभग 115-120 दन होता ह।ै Important one-liners for upcoming exams: रक्त का pH मान कतना होता ह?ै 7.35-7.45 →☛ रक्त म सबस ेअधक मात्रा म कौन सा तत्व पाया जाता ह?ै जल (लगभग 92%) →☛ रक्त का ऑक्सीजन वहन करन ेवाला वणक कौन सा ह?ै हीमोग्लोबन →☛ रक्त म प्लेटलेटस का जीवनकाल कतना होता ह?ै 5-9 दन् →☛ रक्त सल्ेस कहाँ नमत होत ेह? अस्थ मज्जा (बोन मरैो) →☛ Q563.सही उत्तर: दाया ंनलय व्याख्या: मानव हृदय म चार कक्ष होत ेह: दो आलद (ऊपरी कक्ष) और दो नलय (नचल ेकक्ष)। दायां नलय सही उत्तर ह ैक्याक यह दायां आलद स ेवऑक्सीजनत रक्त प्राप्त करता ह ैऔर इसे फुफ्फुसीय धमनी के माध्यम स ेफेफड़ा म अक्सीजनन के लए पपं करता ह।ै यह फुफ्फुसीय परसचंरण का हस्सा ह।ै वकल्प 1 ( बाया ंनलय) गलत ह ैक्याक यह महाधमनी के माध्यम से शरीर म अक्सीजनत रक्त पपं करता ह।ै वकल्प 2 ( दायां आलद) गलत है क्याक यह शरीर से वऑक्सीजनत रक्त प्राप्त करता ह ैलेकन इस ेफेफड़ा म नह पपं करता; यह केवल इस ेदाए नलय म पारत करता ह।ै वकल्प 4 ( बाया ंआलद) गलत ह ैक्याक यह फेफड़ा स ेअक्सीजनत रक्त प्राप्त करता ह।ै मुख्य अवधारणा / प्रक्रया: प्रक्रया/नयम: फुफ्फुसीय परसचंरण - हृदय और फेफड़ा के बीच रक्त का अक्सीजनन के लए परसचंरण। अंग/तत्रं शामल: हृदय / परसचंरण तत्रं वैज्ञानक नाम यद लाग:ू लाग ूनह महत्वपूण मान यद लाग:ू सामान्य मानव हृदय गत: 60-100 प्रत मनट; रक्तचाप: 120/80 mmHg परीक्षा के लए अतरक्त तथ्य: • फुफ्फुसीय धमनी एकमात्र धमनी ह ैजो वऑक्सीजनत रक्त ल ेजाती ह।ै • फुफ्फुसीय शरा एकमात्र शरा ह ैजो अक्सीजनत रक्त ल ेजाती ह।ै • दायां आलद ऊध्व और अधो महाशरा स ेवऑक्सीजनत रक्त प्राप्त करता ह।ै • बायां नलय म सबस ेमोटी पशेीय दीवार होती ह ैताक परूे शरीर म रक्त पपं कया जा सके। • हृदय क पंपग क्रया साइनोएटयल (एसए) नोड द्वारा नयंत्रत होती ह,ै जो प्राकृतक पसेमकेर ह।ै आगामी परीक्षाआ के लए महत्वपूण एक-पंक्त प्रश्न: कौन-सा कक्ष शरीर म अक्सीजनत रक्त पंप करता है? बायां नलय →☛ कौन-सी धमनी वऑक्सीजनत रक्त ले जाती है? फुफ्फुसीय धमनी →☛ फुफ्फुसीय परसचंरण कहा ँहोता है? हृदय और फेफड़ा के बीच →☛ InstBack to Telegram"
      ],
      "correctIndex": 2,
      "explanation": "सही उत्तर विकल्प (C) अर्थात प्लटेलटेस् है।\n\nयह प्रश्न RRB Group D 28 /9/2022 Shift 2 2022 में पूछा गया था।",
      "examName": "RRB Group D 28 /9/2022 Shift 2",
      "examYear": "2022"
    },
    {
      "id": "q_581",
      "type": "standard",
      "question": "श्वसन वणक, हीमोग्लोबन, कहा ँउपस्थत होता ह?ै",
      "options": [
        "श्वेत रक्त कणकाएँ",
        "लाल रक्त कणकाएँ",
        "रक्त प्लटेलटेस",
        "रक्त प्लाज्मा्"
      ],
      "correctIndex": 1,
      "explanation": "सही उत्तर विकल्प (B) अर्थात लाल रक्त कणकाएँ है।\n\nयह प्रश्न RRB Group D 11/10/2022 Shift 2 2022 में पूछा गया था।",
      "examName": "RRB Group D 11/10/2022 Shift 2",
      "examYear": "2022"
    },
    {
      "id": "q_582",
      "type": "standard",
      "question": "इकोकाडयोग्राफ म अल्टासाउंड का प्राथमक उपयोग नम्नलखत म स ेकौन-सा ह?ै (RRB Level 01 Stage I 15/12/2025 9:00 AM - 10:30 AM)",
      "options": [
        "हृदय क संरचना और काय क जाँच करना",
        "धमनया के अवरोधा को साफ़ करना या हटाना",
        "रक्त शकरा के स्तर को मापना",
        "शरीर के वजन का नधारण करना - Circulatory System वऑक्सीजनत रुधर हृदय म कैस ेप्रवेश करता है? दाहने अलद म महाशरा के माध्यम →☛ से Q516.Solution: सही उत्तर ह ैमछली Explanation: मछली का हृदय दो कक्षीय होता ह,ै जसम एक अलद और एक नलय होता ह।ै यह सरल सरंचना रक्त को गलफड़ा तक पपं करती ह,ै जहां ऑक्सीजनीकरण होता ह।ै सरीसृपा म तीन कक्षीय हृदय (दो अलद, एक नलय) पाया जाता ह।ै स्तनधारी और पक्षया म चार कक्षीय हृदय (दो अलद, दो नलय) होता ह।ै दो कक्षीय हृदय केवल मछलया म पाया जाता ह,ै जो उनके जलीय पयावरण के अनुकूल ह।ै Important one-liners for upcoming exams: मछली का हृदय कतन ेकक्षा का होता ह?ै दो (एक अलद, एक नलय) →☛ तीन कक्षीय हृदय कसम पाया जाता ह?ै सरीसपृ →☛ चार कक्षीय हृदय कनम होता ह?ै स्तनधारी और पक्षी →☛ दो कक्षीय हृदय का क्या काय ह?ै रक्त को गलफड़ा तक पपं करना →☛ कस वग म परसचंरण तत्रं सबस ेसरल ह?ै मछली →☛ Q517.Solution: सही उत्तर ह ैस्फग्मोमैनोमीटर Explanation: स्फग्मोमैनोमीटर एक चकत्सा उपकरण ह ैजसका उपयोग रक्तदाब मापने के लए कया जाता ह।ै इसम एक इन्फ्लेटेबल कफ होता ह ैजो बांह के चारा ओर लपटेा जाता ह,ै और एक पारा या एनरॉइड मैनोमीटर होता ह ैजो दबाव दशाता ह।ै रक्तदाब को सस्टोलक (हृदय सकंुचन के दौरान) और डायस्टोलक (हृदय वश्राम के दौरान) दबाव के रूप म व्यक्त कया जाता ह।ै अन्य वकल्प: स्पेक्टोफोटोमीटर प्रकाश अवशोषण मापता ह,ै यूरनोमीटर मत्रू घनत्व मापता ह,ै और हीमोग्लोबन मीटर रक्त म हीमोग्लोबन स्तर मापता ह।ै Important one-liners for upcoming exams: रक्तदाब मापन ेका उपकरण स्फग्मोमनैोमीटर →☛ स्फग्मोमैनोमीटर के आवष्कारक समैअुल सीगफ्राइड काल रटर वॉन बाश →☛ रक्तदाब क इकाइ ममी Hg (पारा का मलीमीटर) →☛ सामान्य रक्तदाब 120/80 mmHg →☛ उच्च रक्तदाब क स्थत हाइपरटशन →☛ Q518.Solution: सही उत्तर ह ैफुफ्फुसीय शरा ऑक्सीजन युक्त रक्त ले जाती ह।ै Explanation: मानव परसचंरण तत्रं म, सामान्य शराए शरीर के वभन्न अगंा स ेडीऑक्सीजनत (काबन डाइऑक्साइड यक्ुत) रक्त हृदय क ओर ले जाती ह। इसके वपरीत, फुफ्फुसीय शरा (pulmonary vein) एकमात्र शरा ह ैजो ऑक्सीजन युक्त रक्त ल ेजाती ह।ै यह रक्त फेफड़ा स ेऑक्सीजन ग्रहण करन ेके बाद हृदय के बाए आलद म पहुचंता ह।ै फुफ्फुसीय शरा म रक्त का प्रवाह नम्न दाब पर होता ह,ै इसका लुमेन बड़ा होता ह,ै और इसम वाल्व नह पाए जात।े इस प्रकार, अन्य शराआ स ेमख्ुय अतंर यह ह ैक यह ऑक्सीजन यक्ुत रक्त ले जाती है, जबक बाक शराए डीऑक्सीजनत रक्त ल ेजाती ह। Index Youtube । धमनयाँ हृदय स ेऑक्सीजनत रक्त को शरीर के वभन्न ऊतका तक ल ेजाती ह (फुफ्फुसीय धमनी को छोड़कर)। हृदय के जोरदार पंपग क्रया के कारण इनम उच्च दबाव होता है। इस दबाव को सहन करन ेके लए, धमनया क मोटी,मांसपेशीय और लचीली दीवार होती ह जो तीन परता से बनी होती ह: ट्यूनका इटंीमा, ट्यूनका मीडया और ट्यूनका एक्सटना। ट्यूनका मीडया म चकनी मांसपेशया ँऔर लचील ेततं ुहोत ेह जो धमनया को फैलने और वापस सकुड़ने म मदद करते ह, जसस ेरक्त प्रवाह बना रहता ह।ै इसके वपरीत, शराआ और शरकाआ क दीवार पतली होती ह जनम कम मांसपेशया ँऔर लचीलापन होता ह ैक्याक य ेनरॉक्सीजनत रक्त को कम दबाव पर हृदय म वापस ल ेजाती ह। केशकाआ क दीवार अत्यतं पतली (एकल एडोथीलयल कोशका परत) होती ह ताक गैसा और पोषक तत्वा का आदान-प्रदान आसानी स ेहो सके। परीक्षा के लए अतरक्त तथ्य: • फुफ्फुसीय धमनी एकमात्र धमनी ह ैजो नरॉक्सीजनत रक्त ल ेजाती ह ै(हृदय स ेफेफड़ा तक)। • कपाट शराआ म रक्त के प्रतवाह को रोकने के लए होत ेह, धमनया म अनुपस्थत होत ेह। • महाधमनी मानव शरीर क सबस ेबड़ी धमनी ह,ै जो बाए नलय स ेनकलती ह।ै • कोरोनरी धमनयाँ हृदय क मांसपशेी को स्वय ंऑक्सीजनत रक्त क आपूत करती ह। • रक्तचाप धमनया म सबस ेअधक और शराआ म सबस ेकम होता ह।ै आगामी परीक्षाआ के लए महत्वपूण एक-पंक्त प्रश्न: कौन-सी रक्त वाहका हृदय स ेरक्त ले जाती है? धमनी →☛ कौन-सी एकमात्र धमनी नरॉक्सीजनत रक्त ले जाती है? फुफ्फुसीय धमनी →☛ प्रतवाह रोकन ेके लए कपाट कहाँ होत ेह? शराआ म →☛ आदान-प्रदान के लए कस वाहका क दीवार सबस ेपतली होती ह? केशकाएँ →☛ मानव शरीर क सबस ेबड़ी धमनी कौन-सी है? महाधमनी →☛ Q523.सही उत्तर: वकल्प 3 — यह शरीर द्वारा ग्लूकोज और वसा के उपयोग और भडंारण को नयंत्रत करता ह।ै व्याख्या: इसंुलन एक पप्ेटाइड हामान ह ैजो अग्न्याशय म लगरहस के द्वीपकाआ के बीटा कोशकाआ द्वारा उत्पादत होता ह।ै इसका प्राथमक काय रक्त ग्लूकोज स्तर को नयंत्रत करना ह,ै जो ग्लूकोज के कोशकाआ (वशेष रूप स ेमांसपेशया और वसा कोशकाआ) म अवशोषण को सुगम बनाकर ऊजा उत्पादन के लए या ग्लाइकोजन के रूप म यकृत और मांसपेशया म, और वसा के रूप म वसा ऊतक म भडंारण करता ह।ै यह यकृत म ग्लूकोनयोजेनेसस ( ग्लूकोज उत्पादन) को भी रोकता ह।ै वकल्प 3 सही ह ैक्याक यह ग्लूकोज और वसा चयापचय म इसंुलन क भूमका का सटीक वणन करता ह।ै वकल्प 1 गलत ह ैक्याक फेफड़ा को ऑक्सीजन क आपूत श्वसन तत्रं का काय ह।ै वकल्प 2 गलत ह ैक्याक रक्त प्रवाह नयत्रंण हृदय, रक्त वाहकाआ और एडेनालाइन जसैे हामान द्वारा नयंत्रत होता ह।ै वकल्प 4 गलत ह ैक्याक हृदय को फ़ल्टर कए गए रक्त क आपूत इसंुलन स ेसबंंधत नह ह;ै हृदय को रक्त कोरोनरी धमनया के माध्यम से प्राप्त होता है। परीक्षा के लए अतरक्त तथ्य: • इसंुलन क कमी या प्रतरोध मधुमेह मेलटस का कारण बनता ह,ै जो हाइपरग्लाइसीमया (उच्च रक्त शकरा) क वशेषता ह।ै • ग्लूकागॉन , अग्न्याशय क अल्फा कोशकाआ द्वारा उत्पादत, इसंुलन के वपरीत प्रभाव डालता है —यह रक्त ग्लूकोज बढ़ाता ह।ै • इसंुलन को पहली बार 1921 म फ्रेडरक बटग और चाल्स बेस्ट द्वारा अलग कया गया था। • टाइप 1 मधुमहे एक ऑटोइम्यनू वकार ह ैजो बीटा कोशकाआ को नष्ट करता ह,ै जसके लए इसंुलन इजंक्ेशन क आवश्यकता होती ह।ै • इसंुलन काबाहाइडेट और वसा चयापचय म अपनी भूमकाआ के अलावा प्रोटीन संेषण को बढ़ावा देता ह ैऔर प्रोटीन वघटन को रोकता ह।ै आगामी परीक्षाआ के लए महत्वपूण एक-पंक्तया:ँ कौन सा हामान रक्त ग्लूकोज स्तर को कम करता है? इसंुलन →☛ मानव शरीर म इसंुलन कहा ँउत्पादत होता है? अग्न्याशय म लगरहस के द्वीपकाआ क →☛ बीटा कोशकाएँ इसंुलन क कमी स ेहोन ेवाला प्राथमक वकार क्या है? मधुमहे मेलटस →☛ कौन सा हामान रक्त ग्लूकोज स्तर बढ़ाता है? ग्लूकागॉन →☛ मनष्ुया म सामान्य उपवास रक्त ग्लूकोज सीमा क्या है? 70–100 mg/dL →☛ Q524.सही उत्तर: बाएँ नलय स ेबाएँ अलद म रक्त का वपरीत प्रवाह व्याख्या: द्ववलनी (मटल) कपाट मानव हृदय म बाएँ अलद और बाएँ नलय के बीच स्थत होता ह।ै Index Youtube Q526.Correct Answer: प्रतरक्षा तत्रं Explanation: एडस (एक्वायड इम्यनूोडेफशएसी सडोम) ह्यमन इम्यूनोडेफशएसी वायरस (HIV) के कारण्ू होता ह।ै यह वायरस वशेष रूप स ेहल्ेपर टी-लम्फोसाइटस (CD4+कोशकाआ) को लक्षत् करता ह ैऔर नष्ट कर देता ह,ै जो शरीर के प्रतरक्षा तत्रं Key Concept / Process: Process/Law: वायरल पथैोजनेेसस और प्रतरक्षा तत्रं का वनाश Organ/System involved: प्रतरक्षा तत्रं (वशेष रूप स ेलसीका तत्रं और CD4+ टी- कोशकाएँ) Scientific name if applicable: Human Immunodeficiency Virus (HIV) Important values if applicable: सामान्य CD4+ गणना: 500–1500 कोशकाएँ/ममी ³; एडस नदान जब CD4+ <200 कोशकाएँ/ममी ³् Extra Facts for Exam: 1. HIV एक रेटोवायरस ह ैजसम आनुवंशक पदाथ के रूप म RNA होता ह।ै 2. वायरस अपन ेgp120 सतह प्रोटीन का उपयोग करके हल्ेपर टी-कोशकाआ पर CD4 रसेप्टस से जड़ुता ह।ै 3. एडस-परभाषत बीमारया म Pneumocystis jirovecii नमोनया, कपोसी सारकोमा और् तपेदक शामल ह। 4. HIV रक्त, वीय, योन द्रव और स्तन के दूध के माध्यम स ेफैल सकता ह।ै 5. एटीरेटोवायरल थरेेपी ( ART) HIV प्रतकृत को नयंत्रत करने म मदद करती ह ैलेकन वायरस को परूी तरह स ेसमाप्त नह करती। Important One-liners for Upcoming Exams: HIVमुख्य रूप स ेकन कोशकाआ को लक्षत करता है? हल्ेपर टी-लम्फोसाइटस (् →☛ CD4+ कोशकाएँ) एडस का पूरा नाम क्या है? एक्वायड इम्यनूोडेफशएसी सडोम् →☛ HIVवायरस के कस परवार स ेसबंंधत है? रेटोवरडी (रेटोवायरस) →☛ HIVम कस प्रकार का आनवुंशक पदाथ होता है? एकल-रज्जकु RNA →☛ HIVसक्रंमण क पुष्ट करन ेवाला नदैानक परीक्षण कौन सा है? ELISA परीक्षण के →☛ बाद वेस्टन ब्लॉट Q527.सही उत्तर: उत्सजन तत्रं व्याख्या: प्रोटीन और न्यूक्लक अम्ला के वघटन के दौरान यूरया , यूरक अम्ल और अमोनया जसैे नाइटोजनी अपशष्ट पदाथ उत्पन्न होत ेह। य ेवषलै ेअपशष्ट मख्ुय रूप स ेउत्सजन तत्रं द्वारा, वशेष रूप स ेवृक्क ( कडनी) के माध्यम स ेहटाए जात ेह, जो मत्रू बनान ेके लए रक्त को छानते ह। परसचंरण तत्रं ( वकल्प 3) इन अपशष्टा को वक्ृक तक पहुचँाता ह ैलेकन उन्ह हटाता नह है। सवंहनी तत्रं ( वकल्प 1) परसचंरण तत्रं का हस्सा ह ैऔर इसी तरह केवल पदाथा का परवहन करता ह।ै श्वसन तत्रं ( वकल्प 4) काबन डाइऑक्साइड हटाता ह,ै नाइटोजनी अपशष्ट नह। इस प्रकार, केवल उत्सजन तत्रं ही शरीर स ेनाइटोजनी उपापचयी अपशष्टा को सीधे नष्कासत करता है। परीक्षा के लए अतरक्त तथ्य: • मानव वृक्क म लगभग 10 लाख नेफ्रॉन होत ेह, जो छानने क क्रयात्मक इकाइयाँ ह। • यूरया यकृत म ऑनथीन चक्र ( यूरया चक्र) के माध्यम स ेउत्पन्न होता ह।ै • अमोनया अत्यधक वषलैा होता ह ैऔर मनुष्य जसै ेस्थलीय जतंआु म यूरया म परवतत हो जाता ह।ै • उत्सजन तत्रं म मत्रूवाहनी, मत्रूाशय और मत्रूमाग भी शामल ह। • पक्षी और सरीसपृ जल सरंक्षण के लए यूरक अम्ल को अध-ठोस पस्ेट के रूप म उत्सजत करते ह। आगामी परीक्षाआ के लए महत्वपूण एक-पंक्त प्रश्न: मनष्ुय म मुख्य उत्सज अंग कौन सा है? वक्ृक →☛ मनष्ुय म प्राथमक नाइटोजनी अपशष्ट क्या है? यूरया →☛ मानव शरीर म यूरया का संषेण कहा ँहोता है? यकृत →☛ कौन सा तत्रं शरीर स ेकाबन डाइऑक्साइड हटाता है? श्वसन तत्रं →☛ वृक्क क क्रयात्मक इकाइ क्या है? नेफ्रॉन →☛ Q528.सही उत्तर: वकल्प 2 — उच्च दाब के साथ रक्त को पपं करने के लए Index Youtube Q530.Solution: सही उत्तर ह ैधमनया क तलुना म शराआ म दाब बहुत अधक होता ह।ै Explanation: यह कथन असत्य ह ैक्याक धमनया म दाब शराआ क तलुना म बहुत अधक होता ह।ै धमनयां हृदय स ेरक्त को दूर ल ेजाती ह और उनम प्रकंुचन दाब (systolic) तथा अनुशथलन दाब (diastolic) होता ह।ै शराआ म दाब कम होता ह ैक्याक वे हृदय क ओर रक्त लौटाती ह और उनम कपाट (valves) होत ेह जो रक्त के पश्च प्रवाह को रोकत ेह। सामान्य रक्तदाब 120/80 mm Hg होता ह।ै रक्तदाब को स्फाइग्मोमैनोमीटर स ेमापा जाता ह।ै Important one-liners for upcoming exams: धमनया म रक्तदाब शराआ क तलुना म कैसा होता ह?ै अधक →☛ नलय सकंुचन के समय का दाब क्या कहलाता ह?ै प्रकुंचन दाब →☛ सामान्य प्रकंुचन दाब कतना होता ह?ै 120 mm Hg →☛ रक्तदाब मापन ेके उपकरण का नाम क्या ह?ै स्फाइग्मोमनैोमीटर →☛ शराआ म रक्त प्रवाह को एकदश बनान ेम क्या सहायक होता ह?ै कपाट →☛ Q531.सही उत्तर: प्रकुंचन; अनुशथलन व्याख्या: रक्तदाब मापन म हृदय चक्र के दो अलग-अलग चरणा के अनुरूप दो मान शामल होते ह। प्रकंुचन दाब उच्चतम मान होता ह ैजो नलय के सकंुचन ( प्रकुंचन) के दौरान दज कया जाता ह,ै जब रक्त धमनया म धकेला जाता ह ैऔर धमनी दीवारा पर अधकतम दाब बनाता है। अनुशथलन दाब नम्नतम मान होता ह ैजो नलय के शथल होन े( अनुशथलन) और रक्त स ेभरन ेके दौरान दज कया जाता ह,ै जो न्यनूतम धमनी दाब का प्रतनधत्व करता ह।ै वकल्प 1 सही ढंग से पहले प्रकुंचन दाब (सकंुचन के दौरान) और फर अनुशथलन दाब (शथलन के दौरान) क पहचान करता ह।ै वकल्प 2 गलत ह ैक्याक शरा दाब मानक रक्तदाब मापन का हस्सा नह है। वकल्प 3 गलत है क्याक \"अधकतम\" प्रकुंचन दाब के लए तकनीक शब्द नह ह।ै वकल्प 4 सही क्रम को उलट देता ह।ै परीक्षा के लए अतरक्त तथ्य: • रक्तदाब धमनदाबमापी द्वारा मापा जाता ह ैजसक इकाइ पारे के मलीमीटर (mmHg) होती ह।ै • उच्च रक्तचाप का नदान तब कया जाता ह ैजब रीडग लगातार 140/90 mmHg स ेअधक होती ह।ै • नाड़ी दाब क गणना प्रकुंचन दाब घटा अनुशथलन दाब के रूप म क जाती है (सामान्य: 40 mmHg) । • रक्तदाब मापन के दौरान प्रकुंचन और अनुशथलन दाब नधारत करन ेके लए कोरोटकोफ ध्वनया का उपयोग कया जाता ह।ै • रक्तदाब आय,ु शारीरक गतवध, तनाव और दन के समय के साथ बदलता रहता है। आगामी परीक्षाआ के लए महत्वपूण एक-पंक्त प्रश्न: वयस्का के लए सामान्य रक्तदाब सीमा क्या है? 120/80 mmHg →☛ रक्तदाब मापन ेवाला उपकरण कौन सा है? धमनदाबमापी →☛ प्रकंुचन दाब क्या दशाता है? नलय सकंुचन के दौरान दाब →☛ 140/90 mmHgस ेअधक रक्तदाब कस स्थत का सकंेत देता है? उच्च रक्तचाप →☛ रक्तदाब मापन के दौरान सनुाइ देन ेवाली ध्वनया को क्या कहत ेह? कोरोटकोफ →☛ ध्वनयाँ Q532.सही उत्तर: गवीनी व्याख्या: मूत्र प्रणाली रक्त स ेअपशष्ट उत्पादा को छानने और उन्ह मत्रू के रूप म उत्सजत करन ेके लए जम्मदेार ह।ै वृक्क मत्रू उत्पन्न करन ेके लए रक्त को छानत ेह, जस ेउत्सजन स ेपहले भंडारण के लए मूत्राशय म ल ेजाने क आवश्यकता होती ह।ै यह परवहन जोड़ीदार पशेीय नलकाआ के माध्यम स ेहोता ह ैजन्ह गवीनी कहा जाता ह।ै प्रत्यके वक्ृक एक गवीनी के माध्यम स ेमत्रूाशय से जड़ुा होता ह,ै जो मत्रू को नीच ेक ओर ले जान ेके लए क्रमाकुंचन सकंुचन का उपयोग करता है। धमनयाँ हृदय स ेऑक्सीजनत रक्त ल ेजाती ह, शराएँ अवॉक्सीजनत रक्त हृदय म वापस ले जाती ह, और महाशरा सबस ेबड़ी शरा ह ैजो रक्त को हृदय म लाती ह—ैइनम स ेकोइ भी मूत्र का परवहन नह करती। इसलए, उत्सजन माग म केवल गवीनी ही इस वशष्ट काय को करती ह। परीक्षा के लए अतरक्त तथ्य: • Index Youtube सस्टोल म क्या होता ह?ै नलय सकंुचत होत ेह और रक्त बाहर नकलता है →☛ रक्त फेफड़ा म कब प्रवेश करता ह?ै सस्टोल म फुफ्फुसीय धमनी के माध्यम से →☛ Q536.Correct Answer: केशकाएँ Explanation: परसचंरण तत्रं रक्त को वाहकाआ के जाल के माध्यम स ेपहुचँाता है। धमनयाँ हृदय से ऑक्सीजनयक्ुत रक्त ले जाती ह और छोटी धमनकाआ म शाखाआ म बटँ जाती ह। य ेधमनकाएँ आग ेसबस ेछोटी रक्त वाहकाआ म वभाजत होती ह जन्ह केशकाएँ कहा जाता ह।ै केशकाआ क भत्तया ँकेवल एक कोशका मोटी होती ह, जो रक्त और आसपास के ऊतका के बीच ऑक्सीजन, पोषक तत्वा और अपशष्ट उत्पादा के कुशल आदान-प्रदान क अनुमत देती ह। यह पतली सरंचना वसरण को सगुम बनाती ह।ै आदान-प्रदान के बाद, केशकाएँ मलकर शरकाएँ बनाती ह, जो फर शराआ म वलीन हो जाती ह जो अशुद्ध रक्त को हृदय म वापस ल ेजाती ह। वकल्प 1 सही ह ैक्याक केशकाआ को वशेष रूप स ेउनक एक-कोशका-मोटी भत्तया द्वारा परभाषत कया जाता ह।ै वकल्प 2 ( शराएँ) और वकल्प 3 ( धमनयाँ) क भत्तयाँ मोटी होती ह और अलग-अलग काय होत ेह। वकल्प 4 ( धमनकाएँ) छोटी धमनया ँह लेकन फर भी केशकाआ क तलुना म मोटी भत्तयाँ होती ह। Key Concept / Process: Process/Law: सक्ष्ूम परसचंरण - ऊतक वनमय के लए केशकाआ के माध्यम से रक्त प्रवाह Organ/System involved: परसचंरण तत्रं / ऊतका म केशका जाल Scientific name if applicable: लाग ूनह Important values if applicable: केशका व्यास: 5-10 माइक्रोमीटर; केशका भत्त मोटाइ: 1 अतंःस्तर कोशका परत Extra Facts for Exam: 1. केशकाएँ रक्त और ऊतका के बीच गसै वनमय (O और CO) और पोषक/अपशष्ट वनमय ₂₂ का स्थल ह। 2. लसीका तत्रं केशका जाल स ेअतरक्त ऊतक द्रव एकत्र करता ह,ै इस ेपरसचंरण म वापस लाता ह।ै 3. छद्रत केशकाएँ म छद्र होत ेह और वक्ृक तथा आतँा म पाइ जाती ह, जो नस्पदंन और अवशोषण के लए होती ह। 4. सतत केशकाएँ म छद्र नह होत ेऔर पेशया तथा तंत्रका ऊतक म पाइ जाती ह। 5. केशका जाल इतने व्यापक ह क शरीर क लगभग हर कोशका एक केशका के 0.1 ममी के भीतर होती ह।ै Important One-liners for Upcoming Exams: कस रक्त वाहका क भत्तयाँ केवल एक कोशकामोटी होती ह? केशकाएँ →☛ रक्त और ऊतका के बीच पदाथा का आदान-प्रदान कहा ँहोता है? केशकाएँ →☛ धमनकाएँ कसम वभाजत होती ह? केशकाएँ →☛ कौन-सी वाहकाएँ धमनकाआ को शरकाआ स ेजोड़ती ह? केशकाएँ →☛ ऊतक वनमय के लए परसचंरण क कायात्मक इकाइ क्या है? केशका जाल →☛ Q537.Solution: सही उत्तर ह ैनलय सकंुचन Explanation: प्रकुंचन रक्तदाब (Systolic blood pressure) वह दबाव ह ैजो हृदय के नलय संकुचन के दौरान रक्त द्वारा धमनया क दीवारा पर लगाया जाता ह।ै जब नलय सकंुचन होता ह,ै तो रक्त को महाधमनी और फुफ्फुसीय धमनी म पपं कया जाता ह,ै जसस ेधमनया म दबाव बढ़ जाता ह।ै यह दबाव अधकतम होता ह ैऔर इस ेप्रकंुचन दाब कहा जाता ह।ै इसके वपरीत, नलय शथलन के दौरान दबाव कम हो जाता ह,ै जस ेअनुशथलन दाब कहत ेह। अलद सकंुचन और अलद शथलन नलय म रक्त भरन ेस ेसबंंधत ह, न क धमनी दाब स।े Important one-liners for upcoming exams: प्रकंुचन दाब कसके सकंुचन के दौरान मापा जाता ह?ै नलय सकंुचन →☛ सामान्य प्रकंुचन दाब का मान क्या होता ह?ै 120 mmHg →☛ धमनी म सबस ेअधक दबाव कब होता ह?ै नलय सकंुचन के दौरान →☛ हृदय चक्र म कस प्रावस्था को सस्टोल कहा जाता ह?ै नलय सकंुचन →☛ डायस्टोल कस प्रावस्था को कहा जाता ह?ै नलय शथलन →☛ Q538.Solution: सही उत्तर ह ैमढक Index Youtube धमनया म रक्त कतन ेदबाव पर बहता ह?ै उच्च दबाव →☛ कौन-सी रक्त वाहका हृदय स ेरक्त ले जाती ह?ै धमनी →☛ Q542.Solution: सही उत्तर ह ैप्लाज्मा Explanation: रक्त का तरल मैटक्स प्लाज्मा कहलाता ह।ै प्लाज्मा रक्त का लगभग 55% भाग होता ह ैऔर इसम 92% जल, 7% प्रोटीन (जसै ेएल्ब्यूमन, ग्लोब्युलन, फाइब्रनोजने) तथा शेष 1% म खनज, ग्लूकोज, हामान और अपशष्ट पदाथ होत ेह। यह रक्त कोशकाआ (RBC, WBC, प्लेटलेटस) को् बहाने का काय करता ह ैऔर पोषक तत्वा, हामाना तथा अपशष्टा के परवहन म सहायक होता है। RBC लाल रक्त कणकाए ऑक्सीजन वाहक ह, WBC प्रतरक्षा म भूमका नभाते ह, और प्लेटलेटस रक्त स्कंदन म सहायक ह, लेकन य ेतीना प्लाज्मा म नलंबत होत ेह, स्वयं मैटक्स नह् ह। अतः सही उत्तर प्लाज्मा ह।ै Important one-liners for upcoming exams: रक्त का तरल मैटक्स प्लाज्मा कहलाता है →☛ प्लाज्मा का प्रमुख घटक जल (92%) →☛ प्लाज्मा म पाया जान ेवाला प्रमुख प्रोटीन एल्ब्यूमन →☛ रक्त स्कंदन म सहायक प्लाज्मा प्रोटीन फाइब्रनोजने →☛ रक्त के कुल आयतन म प्लाज्मा का प्रतशत लगभग 55% →☛ Q543.Solution: सही उत्तर ह ैरक्त केवल सफेद सवंहनी सयंोजी ऊतक है Explanation: रक्त एक तरल सयंोजी ऊतक ह ैजो लाल रक्त कोशकाआ, श्वेत रक्त कोशकाआ, प्लेटलेटस और् प्लाज्मा स ेबना होता ह।ै यह केवल सफेद सवंहनी सयंोजी ऊतक नह ह,ै बल्क इसम लाल कोशकाए भी होती ह। सवंहनी प्रणाली म रक्त, रक्त वाहकाए और हृदय शामल ह। यह प्रणाली शरीर के वजन का लगभग 7-8% बनाती ह।ै एक वयस्क म लगभग 5-6 लीटर रक्त होता है, 6.8 लीटर सामान्य सीमा स ेअधक ह।ै मानव लाल रक्त कोशकाआ का जीवनकाल लगभग 120 दन होता ह।ै इसलए, वकल्प 1 गलत ह।ै Important one-liners for upcoming exams: रक्त कस प्रकार का ऊतक ह?ै तरल सयंोजी ऊतक →☛ रक्त का pH मान कतना होता ह?ै 7.35–7.45 →☛ रक्त का रंग लाल कसके कारण होता ह?ै हीमोग्लोबन →☛ मानव शरीर म रक्त क मात्रा कतनी होती ह?ै शरीर के वजन का 7-8% →☛ लाल रक्त कोशकाआ का नमाण कहा ँहोता ह?ै अस्थ मज्जा →☛ Q544.सही उत्तर: वकल्प 4 — प्रकाश संषेण व्याख्या: वणत प्रक्रया प्रकाश संषेण ह,ै जो एक मौलक चयापचय माग ह ैजसके द्वारा स्वपोषी (मख्ुयतः हरे पौधे, शैवाल और कुछ जीवाण)ु प्रकाश ऊजा को रासायनक ऊजा म परवतत करते ह। स्वपोषी वायमुडंल स ेकाबन डाइऑक्साइड ( CO₂ ) और मट्टी स ेजल ( H₂O ) को कच्च ेपदाथा के रूप म ग्रहण करत ेह। सयू के प्रकाश क उपस्थत म, जस ेक्लोरोप्लास्ट म वणक क्लोरोफल द्वारा अवशोषत कया जाता ह,ै य ेपदाथ प्रकाश-नभर और प्रकाश-स्वतत्रं (केल्वन चक्र) अभक्रयाआ क श्रृंखला स ेगुजरत ेह। इस प्रक्रया म ग्लूकोज ( C₆H₁₂O₆ ) संचत ऊजा के रूप म उत्पन्न होता है और ऑक्सीजन ( O₂ ) एक उपोत्पाद के रूप म मक्ुत होती ह।ै वकल्प4 (प्रकाश संषेण) सही ह ैक्याक यह वशेष रूप स ेइस ऊजा रूपांतरण का वणन करता ह।ै वकल्प1 (परसचंरण) रक्त जसै ेतरल पदाथा के परवहन को सदंभत करता ह,ै ऊजा रूपांतरण को नह। वकल्प2 ( गत)वकल्प3 (पाचन) परीक्षा के लए अतरक्त तथ्य:• प्रकाश संषेणक्लोरोप्लास्टम होता है,वशेष रूप सेथाइलाकोइड झल्ली(प्रकाश अभक्रयाए) औरस्टोमा(केल्वन चक्र) म।• प्राथमक प्रकाश संषेी वणकक्लोरोफल-एहै,जसमसहायक वणक जैस ेक्लोरोफल- बी और कैरोटीनॉइड होत ेह।• C₄ पौधा(जैसे,मक्का,गन्ना) म गम परस्थतया म प्रकाश श्वसन को कम करन ेके लए वशेषक्रांज एनाटॉमीहोती ह।ै• रसायन संषेणकुछ जीवाणआु (जैसे,नाइटीफाइगं जीवाण)ु म एक वैकल्पक प्रक्रया है जो प्रकाश के बजाय रासायनक ऊजा का उपयोग करती ह।ै• प्रकाश संषेण के दौरान मुक्त होन ेवाली ऑक्सीजन जल के प्रकाश-अपघटन स ेआती है, काबन डाइऑक्साइड स ेनह। Index Youtube होता ह।ै Important one-liners for upcoming exams: मनष्ुय के हृदय म कतन ेकक्ष होत ेह? चार →☛ दोहरा परसचंरण कसम पाया जाता ह?ै स्तनधारी और पक्षी →☛ गम रक्त वाले प्राणया को क्या कहा जाता ह?ै एडोथम →☛ एकल परसचंरण कसम पाया जाता ह?ै मछली →☛ मनष्ुय का हृदय कस प्रकार का होता ह?ै चार कक्षीय →☛ Q548.सही उत्तर: हमेोडायलसस व्याख्या: वणत प्रक्रया हमेोडायलसस ह,ै जो गुद क वफलता होन ेपर रक्त स ेअपशष्ट उत्पादा को छानने क एक कृत्रम वध ह।ै वृक्क वफलता म, गुद के नफ्रेॉन पयाप्त रूप स ेउत्सजन और समस्थापन नह कर पात,े जसस ेरक्त म यूरया और अन्य वषाक्त पदाथ जमा हो जात ेह। हमेोडायलसस डायलसस मशीन म एक अधपारगम्य झल्ली का उपयोग करके इन अपशष्ट उत्पादा और अतरक्त तरल पदाथा को रक्तप्रवाह स ेहटाता ह।ै वकल्प 1 ( मलोत्सजन ) गलत है क्याक यह चयापचयी अपशष्टा को समाप्त करने क सामान्य जैवक प्रक्रया को संदभत करता ह,ै वशष्ट कृत्रम उपचार को नह। वकल्प 2 ( उपापचय ) शरीर म सभी रासायनक अभक्रयाआ का योग ह,ै जो गुद के उपचार स ेअसबंंधत ह।ै वकल्प 4 ( परसचंरण ) हृदय प्रणाली के माध्यम से रक्त के सचंलन को सदंभत करता ह,ै शुद्धकरण प्रक्रया को नह। परीक्षा के लए अतरक्त तथ्य: • हमेोडायलसस म आमतौर पर अतं-चरण वक्ृक रोग वाले रोगया के लए सप्ताह म 3 बार, 3–4 घंटे के सत्रा क आवश्यकता होती ह।ै • कृत्रम गदुा ( डायलाइज़र) म अधपारगम्य झल्ली स ेबने खोखले ततं ुहोत ेह जो अपशष्ट उत्पादा के वसरण क अनुमत देत ेह। • हमेोडायलसस के दौरान मशीन म रक्त के थक्के जमन ेस ेरोकने के लए प्रतस्कंदक जसै ेहपेरन का उपयोग कया जाता ह।ै • पेरटोनयल डायलसस एक वैकल्पक वध ह ैजो उदर म पेरटोनयल झल्ली को फल्टर के रूप म उपयोग करती ह।ै • मानव पर पहला सफल हमेोडायलसस डॉ. वलेम कोल्फ़ द्वारा 1943 म द्वतीय वश्व युद्ध के दौरान कया गया था। आगामी परीक्षाआ के लए महत्वपूण एक-पंक्त प्रश्न: गदु वफल होन ेपर रक्त को छानन ेवाली कृत्रम प्रक्रया क्या है? हमेोडायलसस →☛ हमेोडायलसस क आवश्यकता कस अंग क वफलता स ेहोती है? वक्ृक →☛ उदरीय झल्ली का उपयोग करन ेवाला हमेोडायलसस का वकल्प क्या है? →☛ पेरटोनयल डायलसस हमेोडायलसस के दौरान रक्त के थक्के जमन ेस ेक्या रोकता है? प्रतस्कंदक (हपेरन) →☛ मानव पर पहला सफल हमेोडायलसस कसन ेकया था? डॉ. वलेम कोल्फ़ →☛ Q549.Solution: सही उत्तर ह ैमत्स्य Explanation: मत्स्य (मछलया) म एकल-परसचंरण तत्रं पाया जाता ह,ै जसम रक्त प्रत्येक चक्र म हृदय स ेकेवल एक बार गुजरता ह।ै इनका हृदय दो-कक्षीय (एक अलद और एक नलय) होता है। रक्त शरीर से ऑक्सीजन-रहत होकर हृदय म आता ह,ै फर गल्स म ऑक्सीजनत होकर सीधे शरीर म भेजा जाता ह।ै इसके वपरीत, स्तनधारी, पक्षी और सरीसपृ म द्व-परसचंरण तत्रं होता ह,ै जहा ंरक्त दो बार हृदय स ेगुजरता ह ै- एक बार फेफड़ा के लए और एक बार शरीर के लए। मत्स्य म हृदय केवल शरापरक रक्त को पपं करता ह,ै जसस ेऑक्सीजन-रहत और ऑक्सीजनत रक्त मश्रत नह होता। यह एक महत्वपणू वकासात्मक अतंर ह।ै Important one-liners for upcoming exams: एकल-परसचंरण कसम पाया जाता ह?ै मत्स्य →☛ दो-कक्षीय हृदय कसम होता ह?ै मत्स्य →☛ द्व-परसचंरण कसम पाया जाता ह?ै स्तनधारी, पक्षी, सरीसपृ →☛ रक्त हृदय स ेदो बार कब गजुरता ह?ै द्व-परसचंरण म →☛ मत्स्य के हृदय के कक्ष कौन स ेह? एक अलद और एक नलय →☛ Q550.Solution: सही उत्तर ह ैदो Index Youtube Important one-liners for upcoming exams: फुफ्फुस शरा कसम रक्त लाती ह?ै बाएँ अलन्द →☛ महाधमनी (aorta) कहाँ स ेशुरू होती ह?ै बाएँ नलय →☛ फुफ्फुस धमनी (pulmonary artery) कहा ँस ेनकलती ह?ै दाएँ नलय →☛ अवर वेना कावा (inferior vena cava) कहा ँखुलता ह?ै दाएँ अलन्द →☛ हृदय क कौन सी कोष्ठका सबस ेमोटी होती ह?ै बायाँ नलय →☛ Q553.Solution: सही उत्तर ह ै120 और 80 mm Hg Explanation: मनुष्या म सामान्य रक्तदाब 120/80 mm Hg माना जाता ह,ै जसम 120 प्रकुंचन दाब (सस्टोलक) और 80 अनुशथलन दाब (डायस्टोलक) ह।ै यह दाब ब्रैकयल धमनी से मापा जाता है और स्वास्थ्य का महत्वपणू सकंेतक ह।ै 140/90 स ेऊपर उच्च रक्तचाप माना जाता ह ैऔर 90/60 स ेनीच ेनम्न रक्तचाप। रक्तचाप हृदय क प्रत मनट धड़कना और धमनया क लोच पर नभर करता ह।ै हृदय क प्रत्यके धड़कन के दौरान दबाव बदलता ह,ै अधकतम प्रकुंचन और न्यूनतम अनुशथलन। Important one-liners for upcoming exams: उच्च रक्तचाप का सीमा मान (सस्टोलक) 140 mm Hg या अधक →☛ नम्न रक्तचाप का सीमा मान (डायस्टोलक) 60 mm Hg या कम →☛ रक्तचाप मापन ेका उपकरण स्फग्मोमनैोमीटर →☛ सामान्य हृदय गत 72 बीटस प्रत मनट् →☛ रक्तचाप सबस ेअधक प्रभावत होता ह ै धमनी क लोच से →☛ Q554.Solution: सही उत्तर ह ैस्तनधारी, पक्षी और सरीसपृ Explanation: जन जानवरा म रक्त हृदय स ेदो बार गुजरता ह,ै उनम द्वक रक्त सचंार पाया जाता ह।ै इसम रक्त पहले फेफड़ा म ऑक्सीजन लेन ेके लए जाता ह ैऔर फर शरीर म ऑक्सीजन पहुंचाने के लए वापस हृदय म आता ह।ै स्तनधारी (जसै ेमनुष्य), पक्षी और सरीसपृ (जसै ेमगरमच्छ को छोड़कर अधकांश) म यह प्रणाली होती ह।ै वह मछली म एकल रक्त सचंार होता ह,ै जसम रक्त हृदय से केवल एक बार गुजरता ह ैऔर गलफड़ा स ेहोकर सीध ेशरीर म जाता है। इसलए मछली को छोड़कर शेष तीन वगा म द्वक रक्त सचंार पाया जाता ह।ै Important one-liners for upcoming exams: द्वक रक्त सचंार कनम पाया जाता ह?ै स्तनधारी, पक्षी और सरीसपृ →☛ एकल रक्त सचंार कसम होता ह?ै मछली →☛ मनष्ुय का हृदय कतन ेकक्षा का होता ह?ै 4 कक्ष →☛ मछली के हृदय म कतन ेकक्ष होत ेह? 2 कक्ष →☛ कस सरीसपृ म 4 कक्षीय हृदय होता ह?ै मगरमच्छ →☛ Q555.सही उत्तर: वकल्प 3 — पदाथा क पारगम्यता को नयंत्रत करने वाला एक प्रभावी अवरोध बनाने के लए व्याख्या: उपकला ऊतक वशेष ऊतक ह जो शरीर क सतहा को ढकत ेह, आतंरक अगंा को अस्तर करत ेह और ग्रंथया का नमाण करत ेह। इनका प्राथमक काय एक सरुक्षात्मक अवरोध के रूप म काय करना और पदाथा क गत को नयंत्रत करना ह।ै उपकला कोशकाए न्यूनतम अंतरकोशकय स्थान के साथ सघन रूप स ेव्यवस्थत होती ह क्याक यह व्यवस्था एक सतत शीट बनाती है जो रोगजनका के प्रवेश को रोकती ह ैऔर सामग्रया क चयनात्मक पारगम्यता को नयंत्रत करती है। यह सघन व्यवस्था उपकला ऊतका को अवशोषण ( छोटी आंत म), स्राव (ग्रंथया म), और सरुक्षा ( त्वचा म) जसै ेकाय करने म सक्षम बनाती ह।ै वकल्प 1 गलत ह ैक्याक पशेी गत पेशी ऊतका द्वारा सगुम होती ह,ै उपकला ऊतका द्वारा नह। वकल्प 2 गलत ह ैक्याक वद्युत सकंेत सचंरण तंत्रका ऊतका का काय ह।ै वकल्प 4 गलत है क्याक तजे रक्त प्रवाह रक्त वाहकाआ म होता ह ैजो उपकला कोशकाआ द्वारा अस्तरत होती ह, लेकन सघन व्यवस्था स्वय ंरक्त प्रवाह क अनुमत नह देती—यह वाहकाआ का लुमने ह ैजो इसे सभंव बनाता ह।ै परीक्षा के लए अतरक्त तथ्य: • उपकला ऊतक अवाहकय (रक्त वाहकाआ का अभाव) होत ेह और अंतनहत संयोजी ऊतका से वसरण द्वारा पोषक तत्व प्राप्त करत ेह। • Index Youtube कस प्रकार क पेशी हया स ेजुड़ी होती है? कंकाल पशेी →☛ पेशया को हया स ेक्या जोड़ता है? कण्डराएँ →☛ कंकाल पेशयाँ कस तंत्रका तत्रं द्वारा नयंत्रत होती ह? कायक तंत्रका तत्रं →☛ कंकाल पेशयाँ शरीर के वजन का कतना प्रतशतबनाती ह? लगभग 40% →☛ पेशी सकंुचन म कौन स ेप्रोटीन फलामट शामल ह? एक्टन और मायोसन →☛ Q558.Solution: सही उत्तर ह ैलाल रक्त कोशकाआ म Explanation: मानव शरीर म श्वसन वणक हीमोग्लोबन ह,ै जो लाल रक्त कोशकाआ (RBCs) म पाया जाता ह।ै यह ऑक्सीजन को फेफड़ा स ेशरीर के ऊतका तक पहुचंाता ह ैऔर काबन डाइऑक्साइड को वापस लाता ह।ै हीमोग्लोबन म आयरन होता ह,ै जो ऑक्सीजन को बांधन ेम मदद करता ह।ै श्वेत रक्त कोशकाए प्रतरक्षा म भूमका नभाती ह, जबक प्लाज्मा रक्त का तरल भाग है। हीमोग्लोबन का रंग लाल होता ह,ै जो रक्त को लाल रंग देता ह।ै इसक कमी स ेएनीमया होता ह।ै Important one-liners for upcoming exams: मानव श्वसन वणक का नाम हीमोग्लोबन →☛ हीमोग्लोबन कस कोशका म पाया जाता ह ै लाल रक्त कोशकाए →☛ हीमोग्लोबन म उपस्थत धातु लोहा (आयरन) →☛ हीमोग्लोबन का मुख्य काय ऑक्सीजन का परवहन →☛ हीमोग्लोबन क कमी स ेरोग एनीमया →☛ Q559.Solution: सही उत्तर ह ैप्लेटलेटस् Explanation: प्लेटलेटस, जन्ह थ्रोम्बोसाइटस भी कहा जाता ह,ै रक्त का एक प्रमखु घटक है जो थक्के बनाने म्् मदद करता ह।ै जब रक्त वाहका क्षतग्रस्त होती ह,ै तो प्लेटलेटस उस स्थान पर एकत्रत होकर प्लग् बनात ेह और थक्का जमाने वाल ेकारक छोड़त ेह। य ेकारक फाइब्रन नामक प्रोटीन के नमाण को उत्तेजत करत ेह, जो एक जाल बनाकर रक्तस्राव रोकता ह।ै प्लाज्मा प्रोटीन म फाइब्रनोजेन और प्रोथ्रोम्बन जसै ेथक्के बनाने वाल ेकारक होत ेह, लेकन वे प्लेटलेटस के सक्रयण पर नभर करत ेह।् श्वेत और लाल रक्त कोशकाए सीधे थक्के नमाण म शामल नह ह। इस प्रकार, प्लेटलेटस थक्के् के नमाण म प्रमखु भूमका नभात ेह। Important one-liners for upcoming exams: रक्त का कौन सा घटक थक्के नमाण म मुख्य भूमका नभाता ह?ै प्लेटलेटस् →☛ प्लेटलेटस का दूसरा नाम क्या ह?ै थ्रोम्बोसाइटस्् →☛ प्लेटलेटस कहाँ नमत होत ेह? अस्थ मज्जा् →☛ थक्के नमाण म आवश्यक प्रोटीन कौन सा ह?ै फाइब्रनोजने →☛ एक सामान्य व्यक्त म प्लेटलेटस क सख्ंया कतनी होती ह?ै 1.5 स े4.5 लाख प्रत् →☛ माइक्रोलीटर Q560.Solution: सही उत्तर ह ैरक्त सफेद या लाल सवंहनी सयंोजी ऊतक होता ह।ै Explanation: रक्त एक तरल सयंोजी ऊतक ह,ै जो लाल या सफेद नह होता। यह लाल रक्त कोशकाआ (RBC), श्वेत रक्त कोशकाआ (WBC), प्लेटलेटस और प्लाज्मा स ेमलकर बनता ह।ै रक्त का् लाल रंग हीमोग्लोबन के कारण होता ह।ै सवंहनी प्रणाली म हृदय, रक्त वाहकाएँ (धमनयाँ, शराएँ, केशकाएँ) और रक्त शामल ह। यह शरीर के वजन का लगभग 7-8% बनाती है। एक वयस्क म लगभग 5-6 लीटर रक्त होता ह।ै मानव RBC का जीवनकाल लगभग 115-120 दन होता ह।ै अतः वकल्प 3 गलत ह ैक्याक रक्त को 'सफेद या लाल सवंहनी संयोजी ऊतक' कहना सही नह ह।ै Important one-liners for upcoming exams: रक्त कस प्रकार का ऊतक ह?ै तरल सयंोजी ऊतक →☛ रक्त का लाल रंग कसके कारण होता ह?ै हीमोग्लोबन →☛ मानव RBC का जीवनकाल कतना होता ह?ै 115-120 दन →☛ एक वयस्क म रक्त क मात्रा कतनी होती ह?ै 5-6 लीटर →☛ सवंहनी प्रणाली शरीर के वजन का कतना प्रतशत होती ह?ै 7-8% →☛ Q561.Solution: सही उत्तर ह ैमहाधमनी Explanation: महाधमनी मानव शरीर क सबस ेबड़ी धमनी ह ैजो रक्त को हृदय के बाए नलय स ेशरीर के सभी Index Youtube कौन-सी शरा अक्सीजनत रक्त ले जाती है? फुफ्फुसीय शरा →☛ हृदय का पेसमेकर क्या है? साइनोएटयल (एसए) नोड →☛ Q564.सही उत्तर: वकल्प 4 — रक्त वाहका क दीवार के वरुद्ध दबाव डालता है व्याख्या: रक्तचाप को रक्त वाहकाआ, मख्ुय रूप स ेधमनया क दीवारा पर परसचंारी रक्त द्वारा डाल ेगए बल के रूप म परभाषत कया जाता ह।ै यह दबाव हृदय क पंपग क्रया द्वारा उत्पन्न होता ह ैऔर सभी ऊतका म रक्त प्रवाह बनाए रखने के लए आवश्यक ह।ै इस ेमलीमीटर ऑफ मकरी ( mmHg) म मापा जाता ह ैऔर दो माना के रूप म दज कया जाता ह:ै सस्टोलक दबाव ( वटकुलर सकंुचन के दौरान) और डायस्टोलक दबाव ( वटकुलर शथलन के दौरान)। वकल्प 4 सही ह ैक्याक यह इस मौलक परभाषा को सटीक रूप स ेवणत करता है। वकल्प 1 गलत है क्याक दबाव धमनया म अधक होता ह,ै न क नसा म। वकल्प 2 और 3 गलत ह क्याक व ेवशष्ट चरणा (डायस्टोलक और सस्टोलक दबाव) का वणन करत ेह, न क रक्तचाप क सामान्य परभाषा का। परीक्षा के लए अतरक्त तथ्य: • स्फग्मोमैनोमीटर वह उपकरण ह ैजसका उपयोग रक्तचाप मापन ेके लए कया जाता है। • उच्च रक्तचाप (हाइपरटशन) लगातार उच्च रक्तचाप ( >140/90 mmHg) ह।ै • नम्न रक्तचाप (हाइपोटशन) असामान्य रूप स ेकम रक्तचाप (<90/60 mmHg) ह।ै • रक्तचाप महाधमनी म सबस ेअधक होता ह ैऔर रक्त छोटी वाहकाआ म जाने पर कम हो जाता ह।ै • साइनोएटयल नोड (SAनोड) हृदय क धड़कन शुरू करता ह,ै जो रक्तचाप को प्रभावत करता ह।ै आगामी परीक्षाआ के लए महत्वपूण एक-पंक्त प्रश्न: रक्तचाप मापन ेवाले उपकरण को क्या कहत ेह? स्फग्मोमनैोमीटर →☛ एक स्वस्थ वयस्क का सामान्य रक्तचाप क्या होता है? 120/80 mmHg →☛ सस्टोलक दबाव कस चरण के दौरान मापा जाता है? वटकुलर सस्टोल →☛ उच्च रक्तचाप को क्या कहत ेह? हाइपरटशन →☛ हृदय का प्राकृतक पेसमेकर कौन सा नोड है? साइनोएटयल नोड ( SA नोड) →☛ Q565.सही उत्तर: तंत्रका तत्रं व्याख्या: तंत्रका तत्रं स्वायत्त और कायक तंत्रका मागा के माध्यम स ेमत्रूाशय के दाब को नयंत्रत करता है। मूत्राशय एक पशेीय अगं ह ैजो वृक्का द्वारा उत्पादत मत्रू को सग्रंहत करता ह।ै जब मत्रूाशय लगभग 300-400 मलीलीटर भर जाता ह,ै तो इसक दीवार म स्थत खचाव ग्राहीअभवाही तंत्रकाआ के माध्यम स ेमेरुरज्जु और मस्तष्क को सकंेत भजेत ेह। पैरासम्पेथेटक तंत्रका तत्रं तब डटसर पेशी के सकंुचन (दाब बढ़ाना) को प्रेरत करता ह,ै जबक कायक तंत्रका तत्रं मत्रूत्याग के लए बाह्य मूत्रमाग स्फक्टर को शथल करता ह।ै वकल्प 3 सही ह ैक्याक तंत्रकय नयमन भरने और खाली करन ेके दौरान उचत दाब बनाए रखता ह।ै वकल्प 1 ( वृक्क ) केवल मत्रू उत्पन्न करते ह, दाब नयत्रंण नह। वकल्प 2 ( हृदय ) रक्त पपं करता ह ैलेकन मत्रूाशय काय नयंत्रत नह करता। वकल्प 4 ( रक्तचाप ) एक हृदय-सवंहनी मापदंड ह ैजो मत्रूाशय दाब नयत्रंण स ेअसबंंधत ह।ै परीक्षा के लए अतरक्त तथ्य: • मूत्रत्याग कद्र मस्तष्क स्तभं के पॉन्स क्षेत्र म स्थत ह।ै • डटसर पेशी सकंुचन परैासम्पथेेटक तंत्रकाआ द्वारा एसटाइलकोलीन के माध्यम स ेहोता ह।ै • बाह्य स्फक्टर को नयंत्रत करन ेवाली प्यूडडल तंत्रका क क्षत स ेमूत्र असयंम हो सकता ह।ै • आंतरक मूत्रमाग स्फक्टर चकनी पशेी ह ैजो स्वायत्त तंत्रका तत्रं द्वारा अनैच्छक रूप स ेनयंत्रत होती ह।ै • त्रक स्तर स ेऊपर क मेरुरज्जु चोट प्रतवत खाली करने के साथ स्वचालत मूत्राशय का कारण बन सकती ह। आगामी परीक्षाआ के लए महत्वपूण एक-पंक्तया:ँ कौन सा तत्रं मूत्रत्याग प्रतवत को नयंत्रत करता है? तंत्रका तत्रं →☛ मूत्राशय के भरन ेपर क्या मूत्रत्याग को प्रेरत करता है? मरुेरज्ज ुको सकंेत भजेने वाले →☛ खचाव ग्राही कौन सा तंत्रका तत्रं डटसर पेशी को सकंुचत करता है? परैासम्पथेेटक तंत्रका तत्रं →☛ मूत्रत्याग कद्र कहाँ स्थत है? मस्तष्क स्तभं का पॉन्स क्षेत्र →☛ मूत्र सयंम क्या बनाए रखता है? कायक तंत्रकाआ द्वारा नयंत्रत बाह्य मत्रूमाग स्फक्टर →☛ Index Youtube"
      ],
      "correctIndex": 0,
      "explanation": "सही उत्तर विकल्प (A) अर्थात हृदय क संरचना और काय क जाँच करना है।\n\nयह प्रश्न echocardiography में पूछा गया था।",
      "examName": "echocardiography",
      "examYear": ""
    }
  ]
}